{"dataclass_name": "NeuronRecord", "neuron_id": {"dataclass_name": "NeuronId", "layer_index": 3, "neuron_index": 2463}, "most_positive_activation_records": [{"dataclass_name": "ActivationRecord", "tokens": [" a", " coupon", " book", " for", " several", " locations", " in", " Dul", "uth", ".", " I", " would", " definitely", " stay", " here", " again", " on", " future", " trips", " to", " Dul", "uth", ".", "\n", "\n", "Gen", "u", "ine", " Hot", "els", ".", "com", " guest", " review", "\n", "\n", "2", " night", " trip", " Jan", " 17", ",", " 2013", "\n", "\n", "DS", "\n", "\n", "US", "\n", "\n", "3", ".", "0", " /", " 5", "Good", "\n", "\n", "We", " were", " kept", " awake", " most"], "activations": [0.0, 0.0, 0.0, 0.0, 0.0, 0.0, 0.0, 0.0, 0.0, 0.0, 0.0, 0.0, 0.0, 0.0, 0.0, 0.0, 0.0, 0.0, 0.0, 0.0, 0.0, 0.0, 0.0, 0.0, 0.0, 3.6023807525634766, 0.05045270919799805, 0.13336074352264404, 0.0, 0.0, 0.0, 0.0, 0.0, 0.0, 0.0, 0.0, 0.0, 0.0, 0.0, 0.0, 0.0, 0.0, 0.0, 0.0, 0.0, 0.0, 0.0, 0.0, 0.0, 0.0, 0.0, 0.0, 0.0, 0.0, 0.0, 0.0, 0.0, 0.0, 0.0, 0.0, 0.0, 0.0, 0.0, 0.0]}, {"dataclass_name": "ActivationRecord", "tokens": ["A", " Travel", "er", "\n", "\n", "US", "\n", "\n", "4", ".", "0", " /", " 5", "Excellent", "\n", "\n", "\"", "Nic", "ely", " priced", ".\"", "\n", "\n", "Nice", " motel", ".", " In", " better", " shape", " than", " some", " of", " those", " comparatively", " priced", ".", " Location", " next", " to", " I", "-", "35", " was", " not", " a", " problem", ".", "\n", "\n", "Gen", "u", "ine", " Exp", "edia", " guest", " review", "\n", "\n", "Other", " trip", " Mar", " 29", ",", " 2013"], "activations": [0.0, 0.0, 0.0, 0.0, 0.0, 0.0, 0.0, 0.0, 0.0, 0.0, 0.0, 0.0, 0.0, 0.0, 0.0, 0.0, 0.0, 0.0, 0.0, 0.0, 0.0, 0.0, 0.0, 0.0, 0.0, 0.0, 0.0, 0.0, 0.0, 0.0, 0.0, 0.0, 0.0, 0.0, 0.0, 0.0, 0.0, 0.0, 0.0, 0.0, 0.0, 0.0, 0.0, 0.0, 0.0, 0.0, 0.0, 0.0, 0.0, 3.533163070678711, 0.06605756282806396, 0.0564732551574707, 0.0, 0.0, 0.0, 0.0, 0.0, 0.0, 0.0, 0.0, 0.0, 0.0, 0.0, 0.0]}, {"dataclass_name": "ActivationRecord", "tokens": ["ase", " was", " successively", " inactivated", " at", " 60", "\u00b0", "C", " for", " 20", " min", " incubation", ".", " Adapt", "or", " lig", "ated", " amplic", "on", " libraries", " were", " purified", " with", " the", " A", "gen", "court", " AMP", "ure", " XP", " system", " (", "Beck", "man", " Coul", "ter", " Gen", "omics", ",", " Dan", "vers", ",", " MA", ").", " The", " amplic", "on", " libraries", " were", " quantified", " by", " using", " Ion", " Library", " Quant", "itation", " Kit", " (", "Applied", " Biosystems", ",", " Life", " Technologies", ")"], "activations": [0.0, 0.0, 0.0, 0.0, 0.0, 0.0, 0.0, 0.0, 0.0, 0.0, 0.0, 0.0, 0.0, 0.0, 0.0, 0.0, 0.0, 0.44480109214782715, 0.0, 0.0, 0.0, 0.0, 0.0, 0.0, 0.0, 2.2180185317993164, 0.0, 0.0, 0.11070859432220459, 0.0, 0.0, 0.0, 0.0, 0.08609306812286377, 0.18191242218017578, 0.0, 3.343639373779297, 0.1245110034942627, 0.0, 0.4660993814468384, 0.0, 0.0, 0.0, 0.0, 0.0, 0.0, 0.12251341342926025, 0.0, 0.0, 0.0, 0.0, 0.0, 0.05384516716003418, 0.0, 0.0, 0.0, 0.0, 0.0, 0.0, 0.0, 0.0, 0.0, 0.0, 0.0]}, {"dataclass_name": "ActivationRecord", "tokens": ["s", " not", " easy", " to", " get", " it", "*", " \\[", "C", "arer", ",", " F", "G", " Cat", "ania", "\\].", "\n", "\n", "*", "I", "\\'", "d", " like", " more", " information", " about", " what", " \\[", "devices", " and", " aids", "\\]", " are", " available", ";", " we", "\\'", "ve", " only", " just", " found", " out", " about", " the", " existence", " of", " a", " b", "acl", "of", "en", " pump", "*", "...", " \\[", "C", "arer", ",", " F", "G", " Gen", "oa", "\\].", "\n"], "activations": [0.0, 0.0, 0.0, 0.0, 0.0, 0.0, 0.0, 0.0, 0.0, 0.0, 0.0, 0.0, 0.0, 0.0, 0.0, 0.0, 0.0, 0.0, 0.0, 0.0, 0.0, 0.0, 0.0, 0.0, 0.0, 0.0, 0.0, 0.0, 0.0, 0.0, 0.0, 0.0, 0.0, 0.0, 0.0, 0.0, 0.0, 0.0, 0.0, 0.0, 0.0, 0.0, 0.0, 0.0, 0.0, 0.0, 0.0, 0.0, 0.0, 0.0, 0.0, 0.0, 0.0, 0.0, 0.0, 0.0, 0.0, 0.0, 0.0, 0.0, 3.176236629486084, 0.0, 0.0, 0.0]}, {"dataclass_name": "ActivationRecord", "tokens": [" range", " of", " storage", " conditions", ",", " e", ".", "g", ".,", " temperatures", " of", " about", " xe", "2", "x", "88", "x", "9", "240", "xc", "2", "x", "0", " C", ".", " to", " about", " 110", "xc", "2", "x", "0", " C", ".", " Such", " phase", " or", " structural", " changes", " may", " result", " in", " physical", " degradation", " of", " the", " form", " of", " the", " gas", " gener", "ant", " formulation", " such", " as", " when", " such", " gas", " gener", "ant", " formulation", " has", " been", " shaped"], "activations": [0.0, 0.0, 0.0, 0.0, 0.0, 0.0, 0.0, 0.0, 0.0, 0.0, 0.0, 0.0, 0.0, 0.0, 0.0, 0.0, 0.0, 0.0, 0.0, 0.0, 0.0, 0.0, 0.0, 0.0, 0.0, 0.0, 0.0, 0.0, 0.0, 0.0, 0.0, 0.0, 0.0, 0.0, 0.0, 0.0, 0.0, 0.0, 0.0, 0.0, 0.0, 0.0, 0.0, 0.0, 0.0, 0.0, 0.0, 0.0, 0.0, 0.0, 1.741568922996521, 0.0, 0.0, 0.0, 0.0, 0.0, 0.0, 0.0, 1.4443868398666382, 0.0, 0.0, 0.0, 0.0, 0.0]}, {"dataclass_name": "ActivationRecord", "tokens": [".", "\n\n", "    ", "///", " The", " field", " name", " \"", "b", "\"", " fails", " to", " compile", " in", " proto", "1", " because", " it", " conflicts", " with", "\n", "    ", "///", " a", " local", " variable", " named", " \"", "b", "\"", " in", " one", " of", " the", " generated", " methods", ".", "  ", "D", "oh", ".", "\n", "    ", "///", " This", " file", " needs", " to", " compile", " in", " proto", "1", " to", " test", " backwards", "-", "compat", "ibility", ".", "\n", "    ", "var", " bb", ":"], "activations": [0.0, 0.0, 0.0, 0.0, 0.0, 0.0, 0.0, 0.0, 0.0, 0.0, 0.0, 0.0, 0.053809165954589844, 0.0, 0.5782296657562256, 0.10660624504089355, 0.0, 0.0, 0.0, 0.0, 0.0, 0.0, 0.0, 0.0, 0.0, 0.0, 0.0, 0.0, 0.0, 0.0, 0.0, 0.0, 0.0, 0.0, 1.0145800113677979, 0.0, 0.0, 0.0, 0.0, 0.0, 0.0, 0.0, 0.0, 0.0, 0.0, 0.0, 0.0, 0.0, 0.0, 0.0, 0.6152656078338623, 0.047674596309661865, 0.0, 0.0, 0.0, 0.0, 0.0, 0.0, 0.0, 0.0, 0.0, 0.0, 0.0, 0.0]}, {"dataclass_name": "ActivationRecord", "tokens": [" by", " Homer", " to", " make", " a", " tim", "eless", " story", ".", "\n", "610", " BC", ".", " An", "ax", "im", "ander", " (", "Greek", ",", " 610", " BC", "\u2013", "545", " BC", ")", " was", " a", " student", " of", " Th", "ales", " of", " Mile", "t", "us", ".", " The", " first", " life", ",", " he", " taught", ",", " was", " formed", " by", " spontaneous", " generation", " in", " the", " mud", ".", " Later", " animals", " came", " into", " being", " by", " trans", "mut", "ations", ",", " left"], "activations": [0.0, 0.012730896472930908, 0.0, 0.0, 0.0, 0.0, 0.0, 0.0, 0.0, 0.0, 0.0, 0.0, 0.0, 0.0, 0.17857849597930908, 0.0, 0.0, 0.0, 0.0, 0.0, 0.0, 0.0, 0.0, 0.0, 0.0, 0.0, 0.0, 0.0, 0.0, 0.0, 0.0, 0.0, 0.0, 0.0, 0.0, 0.0, 0.0, 0.0, 0.0, 0.0, 0.0, 0.0, 0.0, 0.0, 0.0, 0.0, 0.0, 0.031885504722595215, 0.9994086027145386, 0.0, 0.0, 0.0, 0.0, 0.0, 0.0, 0.0, 0.0, 0.0, 0.0, 0.0, 0.20829808712005615, 0.0, 0.0, 0.0]}, {"dataclass_name": "ActivationRecord", "tokens": [" viral", " RNA", " counterpart", " within", " intracellular", " N", "Cs", ",", " extracellular", " HBV", " RNA", " molecules", " represent", " the", " RNA", " molecules", " generated", " in", " the", " process", " of", " viral", " DNA", " replication", ".", "\n", "\n", "ET", "V", " reduces", " viral", " DNA", " level", " but", " increases", " extracellular", " HBV", " RNA", " level", " in", " naked", " caps", "ids", " and", " vir", "ions", " *", "in", " vitro", "*.", " {#", "s", "2", ".", "6", "}", "\n", "------------------------------------------------------------------------------------------------", "--------------", "\n", "\n", "En", "tec", "avir"], "activations": [0.14139044284820557, 0.0, 0.0, 0.0, 0.0, 0.0, 0.0, 0.0, 0.0, 0.0, 0.0, 0.0, 0.0, 0.0, 0.0, 0.0, 0.947140097618103, 0.0, 0.0, 0.0, 0.0, 0.0, 0.0, 0.0, 0.0, 0.0, 0.0, 0.0, 0.0, 0.0, 0.0, 0.0, 0.0, 0.0, 0.0, 0.0, 0.0, 0.0, 0.0, 0.0, 0.0, 0.0, 0.0, 0.0, 0.16227900981903076, 0.0, 0.0, 0.0, 0.0, 0.0, 0.0, 0.0, 0.0, 0.0, 0.0, 0.0, 0.0, 0.0, 0.0, 0.0, 0.0, 0.0, 0.23175489902496338, 0.0]}, {"dataclass_name": "ActivationRecord", "tokens": [" high", " rate", " of", " successful", " trans", "v", "ag", "inal", " delivery", " after", " selecting", " the", " appropriate", " candidates", ".", "<?", "php", "\n", "\n", "//", " aut", "ol", "oad", "_", "files", ".", "php", " @", "generated", " by", " Com", "poser", "\n", "\n", "$", "vendor", "Dir", " =", " dir", "name", "(", "dirname", "(__", "FILE", "__", "));", "\n", "$", "base", "Dir", " =", " dir", "name", "($", "vendor", "Dir", ");", "\n", "\n", "return", " array", "(", "\n", "    "], "activations": [0.0, 0.08832526206970215, 0.0, 0.0, 0.0, 0.0, 0.0, 0.0, 0.0, 0.0, 0.0, 0.0, 0.0, 0.0, 0.0, 0.0, 0.0, 0.0, 0.0, 0.0, 0.37910401821136475, 0.0, 0.0, 0.0, 0.0, 0.0, 0.0, 0.0, 0.9343248605728149, 0.0, 0.0, 0.0, 0.0, 0.0, 0.0, 0.0, 0.0, 0.0, 0.0, 0.0, 0.0, 0.0, 0.0, 0.0, 0.0, 0.0, 0.0, 0.0, 0.0, 0.0, 0.0, 0.0, 0.0, 0.0, 0.0, 0.0, 0.0, 0.0, 0.0, 0.0, 0.0, 0.0, 0.0, 0.0]}, {"dataclass_name": "ActivationRecord", "tokens": [" up", " the", " national", " credit", " card", "\u201d", " that", " the", " next", " generation", " will", " have", " to", " pay", " off", ".", "\n", "\n", "You", " can", " agree", " or", " disagree", " with", " Obama", "\u2019", "s", " economic", " stimulus", ",", " and", " T", "ARP", ",", " and", " the", " auto", " bail", "outs", " \u2013", " though", " as", " I", " remind", " my", " Republican", " friends", ",", " it", " is", " easy", " to", " critic", "ise", " all", " of", " these", " measures", " and", " claim", " that", " they", " had", " no"], "activations": [0.0, 0.0, 0.0, 0.0, 0.0, 0.0, 0.0, 0.0, 0.0, 0.8798130750656128, 0.0, 0.0, 0.0, 0.0, 0.0, 0.0, 0.0, 0.0, 0.0, 0.0, 0.0, 0.0, 0.0, 0.0, 0.0, 0.0, 0.0, 0.0, 0.0, 0.0, 0.0, 0.0, 0.0, 0.0, 0.0, 0.0, 0.527745246887207, 0.0, 0.0, 0.0, 0.0, 0.0, 0.0, 0.0, 0.0, 0.0, 0.0, 0.0, 0.0, 0.0, 0.0, 0.0, 0.0, 0.0, 0.0, 0.0, 0.0, 0.0, 0.0, 0.0, 0.0, 0.0, 0.0, 0.0]}, {"dataclass_name": "ActivationRecord", "tokens": [" morphology", " of", " these", " organisms", ".", "1", ".", " Field", " of", " Invention", "\n", "Emb", "od", "iments", " of", " the", " present", " invention", " relate", " generally", " to", " a", " method", " and", " apparatus", " for", " retaining", " a", " substrate", " in", " a", " polishing", " system", ".", "\n", "2", ".", " Background", " of", " Invention", "\n", "As", " part", " of", " the", " manufacturing", " process", " of", " semiconductor", " devices", ",", " semiconductor", " wafers", " are", " increasingly", " being", " polished", " by", " C", "MP", ".", " The", " uniform", " removal"], "activations": [0.0, 0.0, 0.0, 0.0, 0.0, 0.0, 0.0, 0.0, 0.0, 0.0, 0.0, 0.0, 0.0, 0.0, 0.0, 0.0, 0.0, 0.0, 0.0, 0.0, 0.0, 0.0, 0.0, 0.0, 0.0, 0.0, 0.0, 0.0, 0.0, 0.0, 0.0, 0.0, 0.0, 0.0, 0.0, 0.0, 0.0, 0.0, 0.0, 0.0, 0.0, 0.0, 0.0, 0.0, 0.0, 0.10178554058074951, 0.0, 0.0, 0.7765148878097534, 0.0, 0.0, 0.8491114377975464, 0.0, 0.0, 0.0, 0.0, 0.0, 0.0, 0.0, 0.0, 0.0, 0.0, 0.0, 0.0]}, {"dataclass_name": "ActivationRecord", "tokens": [" head", ".", " \"", "They", "'ll", " bring", " the", " hunters", " down", " on", " their", " heads", ".\"", "\n", "\n", "\"", "Perhaps", ".", " The", " A", "ven", "aris", " Guild", " has", " re", "group", "ed", " more", " quickly", " than", " I", " anticipated", ".\"", " Domin", "il", " had", " informed", " the", " clan", " that", " a", " new", " group", " of", " experienced", " hunters", " had", " arrived", " in", " the", " country", " from", " Poland", " and", " Croatia", ".", " \"", "The", " Mac", "R", "in", "nal", "chs", " are"], "activations": [0.0, 0.0, 0.0, 0.0, 0.0, 0.0, 0.0, 0.0, 0.0, 0.0, 0.0, 0.0, 0.0, 0.0, 0.0, 0.0, 0.0, 0.0, 0.0, 0.0, 0.8486678600311279, 0.0, 0.0, 0.0, 0.0, 0.0, 0.0, 0.0, 0.0, 0.0, 0.0, 0.0, 0.0, 0.0, 0.0, 0.0, 0.0, 0.0, 0.0, 0.0, 0.0, 0.0, 0.0, 0.0, 0.0, 0.0, 0.0, 0.0, 0.0, 0.0, 0.0, 0.0, 0.0, 0.0, 0.0, 0.0, 0.0, 0.0, 0.0, 0.0, 0.0, 0.0, 0.0, 0.0]}, {"dataclass_name": "ActivationRecord", "tokens": ["Consumer", " immersion", "\u201d", " was", " considered", " the", " most", " powerful", " way", " to", " energ", "ize", " a", " company", "\u2019", "s", " multi", "-", "cultural", " strategy", " and", " summarized", " as", " \u201c", "the", " power", " of", " being", " there", " and", " seeing", " what", "\u2019", "s", " going", " on", ".\u201d", " L", "ever", "aging", " employee", " ethnic", " groups", " within", " organizations", " was", " viewed", " as", " a", " unique", " asset", " companies", " could", " deploy", " to", " generate", " proprietary", " insight", " and", " delight", " and", " win", " with", " diverse"], "activations": [0.1639798879623413, 0.0, 0.0, 0.0, 0.0, 0.0, 0.0, 0.0, 0.0, 0.0, 0.0, 0.0, 0.0, 0.0, 0.0, 0.0, 0.0, 0.0, 0.0, 0.0, 0.0, 0.0, 0.0, 0.0, 0.0, 0.0, 0.0, 0.0, 0.0, 0.0, 0.0, 0.0, 0.0, 0.0, 0.0, 0.0, 0.0, 0.0, 0.0, 0.0, 0.0, 0.0, 0.0, 0.0, 0.0, 0.0, 0.0, 0.0, 0.0, 0.0, 0.0, 0.0, 0.0, 0.0, 0.0, 0.8364114761352539, 0.0, 0.0, 0.0, 0.0, 0.0, 0.0, 0.0, 0.0]}, {"dataclass_name": "ActivationRecord", "tokens": [" and", " electrode", ")", " and", " detection", " parts", " (", "las", "er", " displacement", " sensor", " and", " oscill", "oscope", ").", " The", " schematic", " of", " experimental", " setup", " is", " depicted", " in", " [", "Figure", " 15", "](#", "micromachines", "-", "10", "-", "00", "324", "-", "f", "015", "){", "ref", "-", "type", "=\"", "fig", "\"}.", " Because", " the", " experimental", " conditions", " are", " limited", ",", " the", " geometric", " parameters", " of", " the", " structure", " are", " magn", "ified", ",", " which", " are", " taken", " as"], "activations": [0.0, 0.0, 0.0, 0.0, 0.0, 0.0, 0.0, 0.0, 0.0, 0.0, 0.0, 0.0, 0.0, 0.0, 0.0, 0.0, 0.0, 0.0, 0.0, 0.0, 0.0, 0.0, 0.0, 0.0, 0.0, 0.0, 0.0, 0.0, 0.0, 0.0, 0.0, 0.0, 0.0, 0.0, 0.0, 0.0, 0.0, 0.0, 0.0, 0.0, 0.0, 0.0, 0.0, 0.0, 0.0, 0.0, 0.0, 0.0, 0.0, 0.0, 0.0, 0.0, 0.0, 0.0, 0.0, 0.0, 0.0, 0.8317945003509521, 0.0, 0.0, 0.0, 0.0, 0.0, 0.0]}, {"dataclass_name": "ActivationRecord", "tokens": [" master", " device", " controls", " the", " communication", " and", " assigns", " so", "-", "called", " \u201c", "s", "ends", "l", "ots", "\u201d", " to", " participants", ".", " Additionally", ",", " communications", " within", " a", " p", "icon", "et", " are", " based", " on", " the", " client", " server", " principle", ",", " which", " imposes", " the", " restriction", " that", " the", " master", " (", "server", ")", " is", " needed", " for", " on", "-", "going", " communications", ".", " Thus", ",", " when", " a", " master", " device", " lo", "oses", " the", " connection", " the"], "activations": [0.0, 0.0, 0.0, 0.0, 0.0, 0.0, 0.0, 0.0, 0.0, 0.0, 0.0, 0.0, 0.0, 0.0, 0.0, 0.0, 0.0, 0.0, 0.0, 0.0, 0.0, 0.0, 0.0, 0.0, 0.0, 0.8270049095153809, 0.0, 0.0, 0.0, 0.0, 0.0, 0.0, 0.0, 0.0, 0.0, 0.0, 0.0, 0.0, 0.0, 0.0, 0.0, 0.0, 0.0, 0.0, 0.0, 0.0, 0.0, 0.0, 0.0, 0.0, 0.0, 0.0, 0.0, 0.0, 0.0, 0.0, 0.0, 0.0, 0.0, 0.0, 0.0, 0.0, 0.0, 0.0]}, {"dataclass_name": "ActivationRecord", "tokens": [" U", "-", "phase", " and", " W", "-", "phase", " current", " commands", " are", ",", " subsequently", ",", " fed", " to", " current", " ampl", "ifiers", " 27", "U", ",", " 27", "W", " in", " which", " the", " drive", " currents", " to", " be", " supplied", " to", " the", " U", "-", "phase", " winding", " 7", " and", " the", " W", "-", "phase", " winding", " 9", " are", " generated", " in", " response", " to", " the", " U", "-", "phase", " and", " W", "-", "phase", " current", " commands", ",", " respectively", ".", "\n"], "activations": [0.0, 0.0, 0.0, 0.0, 0.0, 0.0, 0.0, 0.0, 0.0, 0.0, 0.0, 0.0, 0.0, 0.07182478904724121, 0.0, 0.0, 0.4605231285095215, 0.0, 0.0, 0.02664029598236084, 0.0, 0.2564431428909302, 0.0, 0.0, 0.0, 0.0, 0.0, 0.0, 0.0, 0.0, 0.0, 0.0, 0.0, 0.0, 0.0, 0.0, 0.0, 0.0, 0.0, 0.0, 0.0, 0.0, 0.0, 0.0, 0.0, 0.0, 0.8115494251251221, 0.0, 0.0, 0.0, 0.0, 0.0, 0.0, 0.0, 0.0, 0.0, 0.0, 0.0, 0.0, 0.0, 0.0, 0.0, 0.0, 0.0]}, {"dataclass_name": "ActivationRecord", "tokens": ["_", "1", "(", "x", ")=", "x", "$", " and", " induct", "ively", " solve", " the", " O", "DE", " $", "f", "_{", "n", "+", "1", "}'", "=", "e", "^{", "f", "_", "n", "^{-", "1", "}}$", " with", " the", " initial", " condition", " $", "f", "_{", "n", "+", "1", "}(", "0", ")=", "0", "$", " to", " obtain", " $", "f", "_{", "n", "+", "1", "}$,", " much", " in", " the", " spirit", " of", " Pic", "ard", " iteration", ".", " Ex"], "activations": [0.0, 0.0, 0.0, 0.0, 0.0, 0.0, 0.0, 0.0, 0.0, 0.0, 0.0, 0.0, 0.0, 0.0, 0.0, 0.0, 0.0, 0.0, 0.0, 0.0, 0.0, 0.0, 0.0, 0.0, 0.0, 0.0, 0.0, 0.0, 0.0, 0.0, 0.0, 0.0, 0.0, 0.0, 0.0, 0.0, 0.0, 0.0, 0.0, 0.0, 0.0, 0.0, 0.0, 0.0, 0.0, 0.0, 0.0, 0.0, 0.0, 0.0, 0.0, 0.0, 0.0, 0.0, 0.0, 0.0, 0.0, 0.0, 0.0, 0.8098875284194946, 0.0, 0.0, 0.0, 0.0]}, {"dataclass_name": "ActivationRecord", "tokens": [" repositories", " |", " Resources", " >", " Text", "ures", "\n", "\n", "Rob", " Tu", "yt", "el", " has", " launched", " Text", "ure", " Haven", ",", " a", " completely", " free", " to", " use", " crowd", "-", "funded", " P", "BR", " texture", " site", ".", " All", " the", " materials", " come", " with", " bump", ",", " displacement", ",", " normal", ",", " spec", "ular", ",", " diffuse", " and", " roughness", " maps", " available", " under", " a", " CC", "0", " public", " domain", " license", ".", " Ass", "ets", " can", " be", " downloaded", " without"], "activations": [0.0, 0.0, 0.0, 0.0, 0.0, 0.0, 0.0, 0.0, 0.0, 0.0, 0.0, 0.0, 0.0, 0.0, 0.0, 0.0, 0.0, 0.0, 0.0, 0.0, 0.0, 0.0, 0.0, 0.0, 0.0, 0.0, 0.0, 0.0, 0.0, 0.0, 0.0, 0.0, 0.0, 0.0, 0.0, 0.0, 0.0, 0.0, 0.0, 0.0, 0.0, 0.0, 0.8061749935150146, 0.0, 0.0, 0.0, 0.0, 0.0, 0.0, 0.0, 0.0, 0.0, 0.0, 0.0, 0.0, 0.0, 0.0, 0.0, 0.0, 0.0, 0.0, 0.0, 0.0, 0.0]}, {"dataclass_name": "ActivationRecord", "tokens": [" after", " the", " first", " Russian", " edition", ".", " Of", " course", ",", " most", " serious", " chem", "ists", " in", " Europe", " first", " heard", " about", " M", "ende", "le", "ev", "'s", " work", " through", " published", " articles", " rather", " than", " his", " book", ".", " Although", " M", "ende", "le", "ev", " never", " fully", " revised", " his", " textbook", " for", " its", " successive", " editions", ",", " the", " gradual", " evolution", " of", " his", " thoughts", " on", " atomic", " weight", " and", " the", " ordering", " of", " the", " elements", " can", " be"], "activations": [0.0, 0.0, 0.0, 0.0, 0.0, 0.0, 0.0, 0.0, 0.0, 0.0, 0.24277234077453613, 0.782096266746521, 0.0, 0.0, 0.0, 0.0, 0.0, 0.0, 0.0, 0.0, 0.0, 0.0, 0.0, 0.0, 0.0, 0.0, 0.0, 0.0, 0.0, 0.0, 0.0, 0.0, 0.0, 0.0, 0.0, 0.0, 0.0, 0.0, 0.0, 0.0, 0.0, 0.0, 0.0, 0.0, 0.0, 0.0, 0.0, 0.0, 0.0, 0.0, 0.0, 0.0, 0.0, 0.0, 0.0, 0.0, 0.0, 0.0, 0.0, 0.0, 0.0, 0.0, 0.0, 0.0]}, {"dataclass_name": "ActivationRecord", "tokens": [" P", "CC", " and", " T", "FP", "I", " antibody", " throm", "bin", " generation", " was", " activated", " through", " tissue", " factor", ".", " In", " contrast", ",", " the", " added", " F", "FP", " was", " not", " CT", "I", "-", "inhib", "ited", " and", " would", " therefore", " have", " been", " prone", " to", " contact", " activation", " in", " addition", " to", " tissue", " factor", " activation", ".", " Contact", " activation", " has", " previously", " been", " shown", " to", " result", " in", " higher", " E", "TP", " and", " peak", " throm", "bin", " and", " shorter"], "activations": [0.0, 0.0, 0.0, 0.0, 0.0, 0.0, 0.0, 0.0, 0.0, 0.7584455013275146, 0.0, 0.0, 0.0, 0.0, 0.0, 0.0, 0.0, 0.0, 0.0, 0.0, 0.0, 0.0, 0.0, 0.0, 0.0, 0.0, 0.0, 0.0, 0.0, 0.0, 0.0, 0.0, 0.0, 0.0, 0.0, 0.0, 0.0, 0.0, 0.0, 0.0, 0.0, 0.0, 0.0, 0.0, 0.0, 0.0, 0.0, 0.0, 0.0, 0.0, 0.0, 0.0, 0.0, 0.0, 0.0, 0.0, 0.0, 0.0, 0.0, 0.0, 0.0, 0.0, 0.0, 0.0]}, {"dataclass_name": "ActivationRecord", "tokens": ["\n", "Fox", " News", "'", " Lucas", " Tom", "l", "inson", " and", " Elizabeth", " Z", "w", "ir", "z", " contributed", " to", " this", " report", ".", "D", "iver", "gent", " ont", "ogen", "y", " of", " sigma", " and", " phen", "cycl", "idine", " binding", " sites", " in", " the", " rat", " brain", ".", "\n", "The", " postnatal", " developmental", " patterns", " of", " sigma", " (", "sigma", ")", " and", " phen", "cycl", "idine", " (", "PC", "P", ")", " binding", " sites", " were", " compared", " in", " the", " rat", " brain"], "activations": [0.0, 0.0, 0.0, 0.0, 0.0, 0.08110713958740234, 0.0, 0.0, 0.0, 0.0, 0.0, 0.0, 0.0, 0.0, 0.0, 0.0, 0.0, 0.0, 0.0, 0.0, 0.0, 0.0, 0.0, 0.7367982864379883, 0.0, 0.0, 0.0, 0.0, 0.0, 0.0, 0.0, 0.0, 0.0, 0.0, 0.0, 0.0, 0.0, 0.0, 0.0, 0.0, 0.0, 0.0, 0.0, 0.0, 0.0, 0.0, 0.0, 0.0, 0.0, 0.0, 0.0, 0.0, 0.0, 0.0, 0.0, 0.0, 0.0, 0.0, 0.0, 0.0, 0.0, 0.0, 0.0, 0.0]}, {"dataclass_name": "ActivationRecord", "tokens": [".", "\n", "\n", "\"", "Nob", "lemen", " Mart", "on", " and", " Ver", "osus", ",", " greed", " and", " malice", " are", " no", " defense", " against", " treason", ".", " Your", " actions", " solic", "ited", ",", " financed", " and", " facilitated", " an", " act", " of", " rebellion", " against", " us", " and", " against", " this", " Real", "m", ",", " which", " resulted", " in", " the", " death", " of", " several", " subjects", " and", " warriors", " of", " the", " Real", "m", ".", " Moreover", ",", " you", " have", " ext", "orted", " her", " Majesty"], "activations": [0.0, 0.0, 0.0, 0.0, 0.7103079557418823, 0.0, 0.0, 0.0, 0.0, 0.0, 0.0, 0.0, 0.0, 0.0, 0.0, 0.0, 0.0, 0.0, 0.0, 0.0, 0.0, 0.0, 0.0, 0.0, 0.0, 0.0, 0.0, 0.0, 0.0, 0.0, 0.0, 0.0, 0.0, 0.0, 0.0, 0.0, 0.0, 0.0, 0.0, 0.0, 0.0, 0.0, 0.0, 0.0, 0.0, 0.0, 0.0, 0.0, 0.0, 0.0, 0.05792534351348877, 0.0, 0.0, 0.0, 0.0, 0.0, 0.0, 0.0, 0.0, 0.0, 0.0, 0.0, 0.0, 0.0]}, {"dataclass_name": "ActivationRecord", "tokens": [" when", " two", " letters", " picked", " without", " replacement", " from", " f", "bad", "r", ".", "\n", "1", "/", "20", "\n", "Four", " letters", " picked", " without", " replacement", " from", " nob", "so", ".", " What", " is", " p", "Foreign", " minister", " hits", " back", " at", " US", " president", "\u2019", "s", " comments", " on", " suicide", " bombing", " claimed", " by", " Islamic", " State", " that", " killed", " 17", " on", " Wednesday", "\n", "\n", "This", " article", " is", " more", " than", " 3", " years", " old", "\n", "\n", "This", " article"], "activations": [0.0, 0.0, 0.0, 0.0, 0.0, 0.0, 0.0, 0.0, 0.0, 0.0, 0.0, 0.0, 0.03599190711975098, 0.0, 0.0, 0.0, 0.0, 0.0, 0.0, 0.0, 0.0, 0.0, 0.0, 0.0, 0.0, 0.0, 0.0, 0.0, 0.0, 0.0, 0.0, 0.0, 0.0, 0.0, 0.0, 0.0, 0.0, 0.0, 0.0, 0.13404369354248047, 0.0, 0.0, 0.0, 0.7051856517791748, 0.0, 0.0, 0.0, 0.0, 0.0, 0.0, 0.0, 0.0, 0.0, 0.0, 0.0, 0.0, 0.0, 0.0, 0.0, 0.0, 0.0, 0.0, 0.0, 0.0]}, {"dataclass_name": "ActivationRecord", "tokens": ["u", " K", "ato", ",", " new", " president", " and", " CEO", " for", " Honda", " 2", "Whe", "el", "ers", " India", ".", " Out", " of", " the", " new", " product", " line", "-", "up", ",", " one", " will", " be", " the", " Honda", " Africa", " Twin", " adventure", " tou", "rer", " motorcycle", ".", " Honda", " officials", " announced", " that", " they", " have", " started", " trial", " assembly", " for", " the", " Africa", " Twin", ",", " which", " will", " be", " the", " second", " performance", " motorcycle", " by", " Honda", " to", " be", " assembled", " in"], "activations": [0.0, 0.0, 0.0, 0.0, 0.0, 0.0, 0.0, 0.0, 0.0, 0.6967481374740601, 0.0, 0.0, 0.0, 0.0, 0.0, 0.0, 0.0, 0.0, 0.0, 0.0, 0.0, 0.0, 0.0, 0.0, 0.0, 0.0, 0.0, 0.0, 0.0, 0.511894941329956, 0.0, 0.0, 0.0, 0.0, 0.0, 0.07224428653717041, 0.0, 0.3059248924255371, 0.0, 0.0, 0.0, 0.0, 0.0, 0.0, 0.0, 0.0, 0.0, 0.0, 0.0, 0.0, 0.0, 0.0, 0.0, 0.0, 0.0, 0.0, 0.0, 0.0, 0.0, 0.4784061908721924, 0.0, 0.0, 0.0, 0.0]}, {"dataclass_name": "ActivationRecord", "tokens": [" of", " candidates", " identified", " by", " optical", " mapping", "\n", "----------------------------------------------------------------", "---", "\n", "\n", "The", " aim", " of", " this", " study", " is", " to", " generate", " new", " hypotheses", " for", " olig", "odend", "rog", "li", "oma", " genetics", ",", " and", " as", " such", ",", " functional", " studies", " are", " beyond", " the", " scope", " of", " this", " paper", ".", " However", ",", " by", " surve", "ying", " publicly", " available", " data", " on", " the", " candidates", " dis", "cerned", " by", " Optical", " M", "apping", ",", " we", " can", " gain"], "activations": [0.0, 0.0, 0.0, 0.0, 0.0, 0.0, 0.0, 0.0, 0.0, 0.0, 0.0, 0.0, 0.0, 0.0, 0.0, 0.0, 0.0, 0.0, 0.693413496017456, 0.0, 0.0, 0.0, 0.27139604091644287, 0.0, 0.0, 0.0, 0.0, 0.2874513864517212, 0.0, 0.0, 0.0, 0.0, 0.0, 0.0, 0.0, 0.0, 0.0, 0.0, 0.0, 0.0, 0.0, 0.0, 0.0, 0.0, 0.0, 0.0, 0.0, 0.0, 0.0, 0.0, 0.0, 0.0, 0.0, 0.0, 0.05421316623687744, 0.0, 0.0, 0.0, 0.0, 0.0, 0.0, 0.0, 0.0, 0.0]}, {"dataclass_name": "ActivationRecord", "tokens": ["J", "so", " be", " used", " to", " generate", " concise", " source", " code", " reprodu", "cers", " of", " compiler", " and", " runtime", " issues", " we", " uncover", " so", " that", " we", " may", " provide", " them", " to", " relevant", " vendors", " to", " be", " fixed", ".", "\n", "\n", "Here", " the", " deployment", " of", " the", " The", " Filter", " In", "let", " for", " G", "ases", " and", " A", "ER", "Os", "ols", " (", "FIG", "A", "ERO", ")", " coupled", " with", " the", " Aer", "ody", "ne", " High", " Resolution", " ("], "activations": [0.0, 0.0, 0.0, 0.0, 0.0, 0.6910017728805542, 0.05607318878173828, 0.0, 0.0, 0.4050534963607788, 0.0, 0.0, 0.0, 0.0, 0.0, 0.0, 0.0, 0.0, 0.0, 0.0, 0.0, 0.0, 0.0007298588752746582, 0.0, 0.0, 0.0, 0.0, 0.0, 0.0, 0.0, 0.0, 0.0, 0.0, 0.0, 0.0, 0.0, 0.0, 0.0, 0.0, 0.0, 0.0, 0.0, 0.0, 0.0, 0.048765718936920166, 0.0, 0.0, 0.1887965202331543, 0.0, 0.0, 0.0, 0.0, 0.0, 0.0, 0.0, 0.0, 0.0, 0.0, 0.0, 0.0, 0.0, 0.0, 0.0, 0.0]}, {"dataclass_name": "ActivationRecord", "tokens": [" (", "2012", ")", " \u2013", " a", " suspended", " cel", "estial", " figure", " woven", " out", " of", " will", "ow", " branches", " by", " sculpt", "or", " Joy", " Wh", "idd", "ett", ",", " trailing", " the", " words", " '", "peace", "',", " '", "hope", "'", " and", " '", "love", "'.", "\n", "\n", "Outside", " the", " cathedral", "'s", " eastern", " end", " is", " the", " grave", " of", " the", " WW", "I", " hero", "ine", " Edith", " Cav", "ell", ",", " a", " Norfolk", "-", "born", " nurse", " who", " was"], "activations": [0.0, 0.0, 0.0, 0.0, 0.0, 0.0, 0.6702042818069458, 0.0, 0.0, 0.0, 0.0, 0.0, 0.0, 0.0, 0.0, 0.0, 0.0, 0.0, 0.0, 0.0, 0.0, 0.0, 0.0, 0.0, 0.0, 0.0, 0.0, 0.0, 0.0, 0.0, 0.0, 0.0, 0.0, 0.0, 0.0, 0.0, 0.0, 0.0, 0.0, 0.0, 0.0, 0.0, 0.0, 0.0, 0.0, 0.0, 0.0, 0.0, 0.0, 0.0, 0.32154524326324463, 0.0, 0.0, 0.0, 0.0, 0.0, 0.0, 0.0, 0.0, 0.0, 0.0, 0.0, 0.0, 0.0]}, {"dataclass_name": "ActivationRecord", "tokens": ["22", "\u00a0", "\u00b0", "C", "                        ", "        ", "0", ".", "0101", "                        ", "    ", "(", "[@", "ref", "51", "])", "\n", "  ", "\u00a0", "                        ", "                  ", "*", "p", "*-", "NP", "\u00a0", "(", "0", ".", "09", ")", "                        ", "  ", "18", "                        ", "      ", "22", "\u00a0", "\u00b0", "C", "                        ", "        ", "0", ".", "00", "52", "                        ", "    ", "(", "[@", "ref", "51", "])", "\n", "  ", "Ag", "NPs", " on", " fibrous", " nan", "os", "il", "ica", "                "], "activations": [0.0, 0.0, 0.0, 0.0, 0.0, 0.0, 0.0, 0.0, 0.0, 0.0, 0.0, 0.0, 0.0, 0.0, 0.0, 0.0, 0.0, 0.0, 0.0, 0.0, 0.0, 0.0, 0.0, 0.0, 0.0, 0.0, 0.0, 0.0, 0.0, 0.0, 0.0, 0.0, 0.0, 0.0, 0.0, 0.0, 0.0, 0.0, 0.0, 0.0, 0.0, 0.0, 0.0, 0.0, 0.0, 0.0, 0.0, 0.0, 0.0, 0.0, 0.0, 0.0, 0.0, 0.0, 0.0, 0.0, 0.0, 0.0, 0.0, 0.6583547592163086, 0.0, 0.0, 0.0, 0.0]}, {"dataclass_name": "ActivationRecord", "tokens": [" in", " an", " effort", " to", " optimize", " polishing", " pad", " designs", ".", " Most", " of", " the", " polishing", " pad", " developments", " since", " the", " inception", " of", " C", "MP", " as", " a", " semiconductor", " manufacturing", " process", " have", " been", " empirical", " in", " nature", ",", " involving", " trials", " of", " many", " different", " porous", " and", " non", "-", "por", "ous", " polymeric", " materials", ".", " Much", " of", " the", " design", " of", " polishing", " surfaces", ",", " or", " layers", ",", " has", " focused", " on", " providing", " these", " layers", " with"], "activations": [0.0, 0.0, 0.0, 0.0, 0.0, 0.0, 0.0, 0.0, 0.0, 0.0, 0.0, 0.0, 0.020282745361328125, 0.0, 0.0, 0.0, 0.0, 0.0, 0.0, 0.0, 0.0, 0.0, 0.0, 0.6571080684661865, 0.18426477909088135, 0.0, 0.0, 0.0, 0.0, 0.0, 0.0, 0.0, 0.0, 0.0, 0.0, 0.0, 0.0, 0.0, 0.0, 0.0, 0.0, 0.0, 0.0, 0.13004326820373535, 0.0, 0.0, 0.0, 0.0, 0.0, 0.0, 0.0, 0.0, 0.0, 0.0, 0.0, 0.0, 0.0, 0.0, 0.0, 0.0, 0.0, 0.0, 0.0, 0.0]}, {"dataclass_name": "ActivationRecord", "tokens": [" \"", "Ms", " Williams", "\"", " in", " her", " upcoming", " movie", " Battle", "field", " America", ",", " blog", "spot", " readers", ".", " Don", "'t", " let", " the", " movie", " title", " alone", " scare", " you", " into", " thinking", " it", "'s", " another", " Us", " versus", " Ali", "ens", " bent", " on", " dest", "ory", "ing", " the", " world", " coming", " to", " a", " multi", "-", "plex", " near", " you", " this", " summer", ".", " No", "pe", " ...", "no", " transforming", " aliens", " -", " this", " is", " a", " dance", " competition"], "activations": [0.0, 0.0, 0.0, 0.0, 0.0, 0.0, 0.0, 0.0, 0.0, 0.0, 0.0, 0.0, 0.0, 0.0, 0.0, 0.0, 0.0, 0.0, 0.0, 0.0, 0.0, 0.0, 0.0, 0.6262848377227783, 0.0, 0.0, 0.0, 0.0, 0.0, 0.0, 0.0, 0.0, 0.0, 0.0, 0.0, 0.0, 0.0, 0.0, 0.0, 0.0, 0.0, 0.0, 0.0, 0.0, 0.09310805797576904, 0.0, 0.0, 0.0, 0.0, 0.0, 0.0, 0.0, 0.007371842861175537, 0.0, 0.0, 0.0, 0.0, 0.0, 0.0, 0.0, 0.0, 0.0, 0.0, 0.0]}, {"dataclass_name": "ActivationRecord", "tokens": [" 57", " months", " (", "5", "-", "96", "),", " the", " estimated", " five", "-", "year", " disease", "-", "free", " survival", " was", " 78", "%.", " Global", " survival", " estimated", " to", " 60", " months", " was", " 83", "%", " for", " stage", " IB", "2", ",", " 70", "%", " for", " II", "B", ",", " and", " 20", "%", " for", " III", "B", ".", " This", " mode", " of", " therapy", " offers", " a", " new", " option", " to", " improve", " survival", " in", " locally", " advanced", " cervical", " cancer", ".", " Random"], "activations": [0.0, 0.0, 0.0, 0.0, 0.0, 0.0, 0.0, 0.0, 0.0, 0.0, 0.0, 0.0, 0.0, 0.0, 0.0, 0.0, 0.0, 0.0, 0.0, 0.0, 0.0, 0.0, 0.0, 0.0, 0.0, 0.0, 0.0, 0.0, 0.0, 0.0, 0.0, 0.0, 0.0, 0.0, 0.0, 0.0, 0.10386192798614502, 0.0, 0.0, 0.0, 0.0, 0.0, 0.0, 0.6216539144515991, 0.0, 0.0, 0.0, 0.0, 0.0, 0.0, 0.0, 0.0, 0.0, 0.0, 0.0, 0.0, 0.0, 0.0, 0.0, 0.0, 0.0, 0.0, 0.0, 0.0]}, {"dataclass_name": "ActivationRecord", "tokens": ["29", " days", "\n", "Cert", "ified", " Pre", "-", "Own", "ed", ":", " No", "\n", "Trans", "mission", ":", " Automatic", "\n", "Color", ":", " White", "\n", "Description", ":", "\n", "Used", " 2012", " Honda", " Acc", "ord", " SE", " for", " sale", "\n", "-", " $", "12", ",", "350", ",", " 38", ",", "683", " miles", " with", " Le", "ather", " Se", "ats", ",", "\n", "All", "oy", " Whe", "els", "\n", "\n", "Av", "g", ".", " Deal", "er", " Rating", ":", " ("], "activations": [0.0, 0.0, 0.0, 0.0, 0.0, 0.0, 0.0, 0.0, 0.0, 0.0, 0.0, 0.0, 0.0, 0.0, 0.0, 0.0, 0.0, 0.0, 0.0, 0.0, 0.0, 0.0, 0.0, 0.0, 0.0, 0.0, 0.6179566383361816, 0.22543907165527344, 0.0, 0.0, 0.0, 0.0, 0.0, 0.0, 0.0, 0.0, 0.0, 0.0, 0.0, 0.0, 0.0, 0.0, 0.0, 0.0, 0.0, 0.0, 0.0, 0.0, 0.0, 0.0, 0.0, 0.0, 0.0, 0.0, 0.0, 0.0, 0.0, 0.0, 0.0, 0.0, 0.0, 0.0, 0.0, 0.0]}, {"dataclass_name": "ActivationRecord", "tokens": ["y", " Daniels", "\u2019", " attorney", " Michael", " A", "ven", "atti", ".", " This", " facilitated", " inc", "end", "iary", " statements", " from", " A", "ven", "atti", " which", " made", " it", " very", " clear", " that", " he", " does", " not", " believe", " the", " currently", " accepted", " version", " of", " the", " story", ",", " and", " that", " he", " intends", " to", " dep", "ose", " Be", "chard", " himself", " as", " early", " as", " July", " 16", "th", ".", "\n", "\n", "There", " are", " those", " in", " the", " small", " legal", " community"], "activations": [0.0, 0.0, 0.0, 0.0, 0.0, 0.0, 0.6140439510345459, 0.0, 0.0, 0.0, 0.0, 0.0, 0.0, 0.0, 0.0, 0.0, 0.0, 0.5606182813644409, 0.0, 0.0, 0.0, 0.0, 0.0, 0.0, 0.0, 0.0, 0.0, 0.0, 0.0, 0.0, 0.0, 0.0, 0.0, 0.0, 0.0, 0.0, 0.0, 0.0, 0.0, 0.0, 0.0, 0.0, 0.0, 0.0, 0.0, 0.0, 0.0, 0.0, 0.0, 0.0, 0.0, 0.0, 0.0, 0.0, 0.0, 0.0, 0.0, 0.0, 0.0, 0.0, 0.0, 0.0, 0.0, 0.0]}, {"dataclass_name": "ActivationRecord", "tokens": ["-", "00", "113", "],[@", "B", "11", "-", "nanomaterials", "-", "02", "-", "00", "113", "],[@", "B", "12", "-", "nanomaterials", "-", "02", "-", "00", "113", "],[@", "B", "13", "-", "nanomaterials", "-", "02", "-", "00", "113", "],[@", "B", "14", "-", "nanomaterials", "-", "02", "-", "00", "113", "]\\].", " Molecular", " precursor", " approach", " has", " recently", " been", " developed", " as", " an", " efficient", " route", " to", " prepare", " mon", "od", "is", "pers", "ed", " semiconductor", " nanoc"], "activations": [0.0, 0.0, 0.041594862937927246, 0.0, 0.0, 0.0, 0.0, 0.0, 0.0, 0.0, 0.0, 0.0, 0.0, 0.0, 0.0, 0.0, 0.0, 0.0, 0.0, 0.0, 0.0, 0.0, 0.0, 0.0, 0.0, 0.0, 0.0, 0.0, 0.0, 0.0, 0.0, 0.0, 0.0, 0.0, 0.0, 0.0, 0.0, 0.0, 0.0, 0.0, 0.0, 0.0, 0.0, 0.0, 0.25955629348754883, 0.0, 0.0, 0.0, 0.0, 0.0, 0.0, 0.0, 0.0, 0.0, 0.0, 0.0, 0.0, 0.35028839111328125, 0.0, 0.0, 0.0, 0.0, 0.6033049821853638, 0.1226738691329956]}, {"dataclass_name": "ActivationRecord", "tokens": ["bo", " mother", " and", " her", " master", ",", " John", " Wright", " Stan", "ly", "\u2014", "bec", "ame", " an", " extraordinarily", " successful", " bar", "ber", " and", " spec", "ulator", " in", " real", " estate", " in", " New", " Bern", ".", " As", " Loren", " Schw", "ening", "er", " points", " out", " in", " Black", " Property", " Own", "ers", " in", " the", " South", ",", " 17", "90", "-", "19", "15", ",", " by", " the", " early", " 18", "20", "s", ",", " Stan", "ly", " owned", " three", " plant", "ations", " and"], "activations": [0.0, 0.0, 0.0, 0.0, 0.0, 0.0, 0.0, 0.0, 0.0, 0.0, 0.0, 0.0, 0.0, 0.0, 0.0, 0.0, 0.0, 0.0, 0.0, 0.5969314575195312, 0.013794898986816406, 0.0, 0.0, 0.0, 0.0, 0.0, 0.0, 0.0, 0.0, 0.0, 0.0, 0.0, 0.0, 0.0, 0.0, 0.0, 0.0, 0.0, 0.0, 0.0, 0.0, 0.0, 0.0, 0.0, 0.0, 0.0, 0.0, 0.0, 0.0, 0.0, 0.0, 0.0, 0.0, 0.0, 0.0, 0.0, 0.0, 0.0, 0.0, 0.0, 0.0, 0.0, 0.0, 0.0]}, {"dataclass_name": "ActivationRecord", "tokens": ["og", "istic", " inference", " task", " required", " participants", " to", " generate", " and", " write", " the", " solution", " to", " five", " syll", "og", "isms", ".", " These", " syll", "og", "isms", " included", " the", " combinations", " of", " the", " four", " kinds", " of", " premises", ":", " universal", " affirmative", " (", "A", ":", " All", " X", " are", " Y", "),", " universal", " negative", " (", "E", ":", " No", " X", " are", " Y", "),", " particular", " affirmative", " (", "I", ":", " Some", " X", " are", " Y", ")", " and", " particular"], "activations": [0.0, 0.0, 0.0, 0.0, 0.0, 0.0, 0.0, 0.5958613157272339, 0.0, 0.0, 0.0, 0.0, 0.0, 0.0, 0.0, 0.0, 0.0, 0.0, 0.0, 0.0, 0.0, 0.0, 0.0, 0.0, 0.0, 0.0, 0.0, 0.0, 0.0, 0.0, 0.0, 0.0, 0.19677138328552246, 0.0, 0.0, 0.0, 0.0, 0.0, 0.0, 0.0, 0.0, 0.0, 0.15163981914520264, 0.0, 0.0, 0.0, 0.0, 0.0, 0.0, 0.0, 0.0, 0.0, 0.0, 0.0, 0.0, 0.0, 0.0, 0.0, 0.0, 0.0, 0.0, 0.0, 0.0, 0.0]}, {"dataclass_name": "ActivationRecord", "tokens": [" cytotoxic", " substances", ".", " In", " the", " present", " study", ",", " multi", "-", "factor", "ial", " drug", "-", "resistant", " cancer", " cell", " lines", " such", " as", " leukemia", " C", "EM", "/", "AD", "R", "5000", " cells", " over", "-", "expressing", " P", "-", "gp", ",", " breast", " adenocarcinoma", " MDA", "-", "MB", "-", "231", "-*", "B", "CRP", "*", " clone", " 23", " expressing", " B", "CRP", ",", " EGFR", "-", "transfected", " U", "87", "MG", ".", "\u0394", "*", "EGFR", "*", " gli"], "activations": [0.0, 0.0, 0.0, 0.0, 0.0, 0.0, 0.0, 0.0, 0.0, 0.0, 0.028814613819122314, 0.0, 0.0, 0.0, 0.0840538740158081, 0.0, 0.0, 0.0, 0.0, 0.0, 0.0, 0.0, 0.0, 0.0, 0.0, 0.0, 0.0, 0.0, 0.0, 0.0, 0.0, 0.0, 0.0, 0.0, 0.0, 0.0, 0.0, 0.0, 0.0, 0.0, 0.0, 0.0, 0.0, 0.0, 0.0, 0.0, 0.5895144939422607, 0.0, 0.0, 0.0, 0.0, 0.0, 0.14752018451690674, 0.0, 0.0, 0.0, 0.0, 0.0, 0.0, 0.0, 0.0, 0.0, 0.0, 0.22288239002227783]}, {"dataclass_name": "ActivationRecord", "tokens": [")=", "0", ",", " \n", " \\", "end", "{", "cases", "}$$", "\n", "that", " generates", " the", " sequence", " O", "E", "IS", " A", "0010", "28", ".", " ", "\n", "As", " before", ",", " a", " maxim", "ally", "-", "defined", " analytic", " solution", " $", "g", "$,", " if", " any", ",", " must", " be", " totally", " monotonic", " and", " defined", " for", " all", "  ", "$", "x", "\\", "ge", "0", "$,", " for", " otherwise", " $", " g", "'\\", "circ", " g", "^{-", "1", "}"], "activations": [0.0, 0.0, 0.0, 0.0, 0.0, 0.0, 0.0, 0.0, 0.0, 0.0, 0.0, 0.586138129234314, 0.0, 0.0, 0.0, 0.0, 0.0, 0.0, 0.0, 0.0, 0.0, 0.0, 0.0, 0.0, 0.0, 0.0, 0.0, 0.0, 0.0, 0.0, 0.0, 0.0, 0.0, 0.0, 0.0, 0.0, 0.0, 0.0, 0.0, 0.0, 0.0, 0.0, 0.0, 0.0, 0.0, 0.0, 0.0, 0.0, 0.0, 0.0, 0.0, 0.0, 0.0, 0.0, 0.0, 0.0, 0.0, 0.04378777742385864, 0.0, 0.0, 0.19090759754180908, 0.0, 0.0, 0.0]}, {"dataclass_name": "ActivationRecord", "tokens": ["64", "\\", "6", "111", "\\", "include", "\\", "omi", "_", "Bl", "k", "Bit", "V", "ect", "T", "rav", ".", "h", " 69", "  ", "1", "   ", "Reader", "\n", "Warning", " C", "4", "244", ":", " '", "initial", "izing", "'", " :", " conversion", " from", " '", "double", "'", " to", " '", "float", "',", " possible", " loss", " of", " data", ".", " C", ":\\", "Users", "\\", "mc", "gre", "te", "\\", "Documents", "\\", "i", "CO", "B", "RA", "\\", "pts"], "activations": [0.0, 0.0, 0.0, 0.0, 0.0, 0.0, 0.0, 0.0, 0.0, 0.0, 0.0, 0.0, 0.0, 0.0, 0.0, 0.0, 0.0, 0.0, 0.0, 0.0, 0.0, 0.0, 0.0, 0.0, 0.0, 0.0, 0.0, 0.0, 0.0, 0.0, 0.0, 0.0, 0.0, 0.0, 0.5736204385757446, 0.0, 0.0, 0.0, 0.0, 0.0, 0.0, 0.0, 0.0, 0.0, 0.0, 0.0, 0.0, 0.0, 0.0, 0.0, 0.0, 0.0, 0.0, 0.0, 0.0, 0.0, 0.0, 0.0, 0.0, 0.0, 0.0, 0.0013391971588134766, 0.0, 0.0]}, {"dataclass_name": "ActivationRecord", "tokens": [" Both", " these", " classes", " of", " genomic", " elements", " provide", " an", " additional", " tier", " of", " gene", " regulation", ",", " and", " contribute", " significantly", " to", " the", " transcriptional", " landscape", " of", " human", " cancers", " \\[[@", "B", "134", "],[@", "B", "135", "]\\].", " Several", " candidates", " also", " show", " interesting", " changes", " in", " their", " putative", " functions", " in", " cancer", " tissues", ".", " For", " example", ",", " we", " observe", " a", " MC", " on", " chromosome", " 2", " (", "HF", "087", ")", " in", " a", " genomic", " region", " bearing"], "activations": [0.0, 0.0, 0.0, 0.0, 0.5667258501052856, 0.0, 0.0, 0.0, 0.0, 0.0, 0.0, 0.0, 0.0, 0.0, 0.0, 0.0, 0.0, 0.0, 0.0, 0.0, 0.0, 0.0, 0.0, 0.0, 0.0, 0.0, 0.0, 0.0, 0.0, 0.0, 0.0, 0.0, 0.0, 0.0, 0.0, 0.0, 0.0, 0.0, 0.0, 0.0, 0.0, 0.0, 0.0, 0.0, 0.0, 0.0, 0.0, 0.0, 0.0, 0.0, 0.0, 0.0, 0.0, 0.0, 0.0, 0.0, 0.0, 0.0, 0.0, 0.0, 0.0, 0.4211132526397705, 0.0, 0.0]}, {"dataclass_name": "ActivationRecord", "tokens": ["WF", " antigen", " (", "IU", "/", "dl", ")", "               ", "144", "                   ", "170", "                       ", "\\<", "0", ".", "0001", "\n", "                        ", "            ", "61", "--", "322", " (", "113", "--", "184", ")", "    ", "84", "-", "367", " (", "131", "--", "205", ")", "         ", "\n", "  ", "F", "ibr", "in", "ogen", " (", "g", "/", "l", ")", "                  ", "3", ".", "2", "                   ", "1", ".", "6", "                       ", "\\<", "0", ".", "0001", "\n", "                        ", "            "], "activations": [0.0, 0.45802581310272217, 0.0, 0.0, 0.0, 0.0, 0.0, 0.0, 0.0, 0.0, 0.0, 0.0, 0.0, 0.0, 0.0, 0.0, 0.0, 0.0, 0.0, 0.0, 0.0, 0.0, 0.0, 0.0, 0.0, 0.0, 0.0, 0.0, 0.0, 0.0, 0.0, 0.0, 0.0, 0.0, 0.0, 0.0, 0.0, 0.0, 0.0, 0.0, 0.0, 0.0, 0.5643572807312012, 0.0, 0.0, 0.0, 0.0, 0.0, 0.0, 0.0, 0.0, 0.0, 0.0, 0.0, 0.0, 0.0, 0.0, 0.0, 0.0, 0.0, 0.0, 0.0, 0.0, 0.0]}, {"dataclass_name": "ActivationRecord", "tokens": [" function", "()", " {};", "').", "decl", "ar", "ations", "[", "0", "].", "init", ";", "\n", "    ", "const", " function", "Expression", "2", " =", " parse", "('", "var", " foo", " =", " function", "(", "bar", ")", " {};", "').", "decl", "ar", "ations", "[", "0", "].", "init", ";", "\n", "    ", "const", " identifier", " =", " parse", "('", "foo", ";", "').", "expression", ";", "\n", "    ", "const", " literal", " =", " parse", "('", "1", ";", "').", "expression", ";", "\n", "    "], "activations": [0.0, 0.0, 0.0, 0.0, 0.0, 0.0, 0.0, 0.0, 0.0, 0.0, 0.15468645095825195, 0.0, 0.0, 0.0, 0.0, 0.0, 0.0, 0.0, 0.0, 0.14399361610412598, 0.0, 0.0, 0.0, 0.0, 0.0, 0.0, 0.0, 0.0, 0.0, 0.0, 0.0, 0.0, 0.0, 0.0, 0.0, 0.0, 0.0860743522644043, 0.0, 0.0, 0.0, 0.0, 0.0, 0.0, 0.5244216918945312, 0.0, 0.0, 0.0, 0.0, 0.0, 0.0, 0.0, 0.0, 0.0, 0.0, 0.0, 0.5616672039031982, 0.0, 0.0, 0.0, 0.0, 0.0, 0.0, 0.0, 0.0]}, {"dataclass_name": "ActivationRecord", "tokens": [" Please", " enter", " a", " p", "ang", "ram", "ic", " sentence", "   ", "(", "or", " a", " blank", " to", " quit", "):", "\n", "                        ", "                        ", "   ", "\ufffd", "\ufffd", "\u25a0", "\u25a0", "\u25a0", "\u25a0", "\u25a0", "\u25a0", "\u25a0", "\u25a0", "\u25a0", "\u25a0", " user", " input", "   ", "(", "null", "  ", "or", "  ", "some", " bl", "anks", ").", "\n", "\n", "\u2500\u2500\u2500\u2500\u2500\u2500\u2500\u2500", " PAN", "GRAM", " program", " ended", ".", " \ufffd", "\ufffd", "\u2500\u2500\u2500\u2500", "\u2500\u2500", "\u2500", "\n", "\n", "```", "\n\n\n", "\n", "##", " Ring"], "activations": [0.0, 0.0, 0.0, 0.0, 0.0, 0.0, 0.0, 0.0, 0.0, 0.0, 0.0, 0.0, 0.0, 0.0, 0.0, 0.0, 0.0, 0.0, 0.0, 0.0, 0.2855931520462036, 0.04027128219604492, 0.0, 0.18755078315734863, 0.29337358474731445, 0.3659864664077759, 0.42096471786499023, 0.45420753955841064, 0.48180460929870605, 0.5103029012680054, 0.5372586250305176, 0.560510516166687, 0.0, 0.0, 0.0, 0.0, 0.0, 0.0, 0.0, 0.0, 0.0, 0.0, 0.0, 0.0, 0.0, 0.0, 0.0, 0.0, 0.0, 0.0, 0.0, 0.0, 0.0, 0.0, 0.14098358154296875, 0.30202555656433105, 0.09125542640686035, 0.0, 0.0, 0.0, 0.0, 0.0, 0.0, 0.0]}, {"dataclass_name": "ActivationRecord", "tokens": [" for", " the", "\n", "    ", "conversion", ",", " but", " only", " if", " the", " fields", " are", " also", " accessed", " outside", " the", "\n", "    ", "conversion", ".", "\n", "  ", "-", " (", "5", ".", "2", ")", " when", " converting", " to", " or", " from", " unsafe", ".", "Pointer", ",", " mark", " all", " fields", " as", " used", ".", "\n", "\n", "-", " struct", "s", " use", ":", "\n", "  ", "-", " (", "6", ".", "1", ")", " fields", " of", " type", " No", "Copy", " sent"], "activations": [0.0, 0.0, 0.0, 0.0, 0.5574657917022705, 0.0, 0.0, 0.0, 0.0, 0.0, 0.0, 0.0, 0.0, 0.0, 0.0, 0.0, 0.0, 0.0, 0.23580431938171387, 0.0, 0.0, 0.0, 0.0, 0.0, 0.0, 0.0, 0.0, 0.0, 0.0, 0.011815965175628662, 0.0, 0.0, 0.0, 0.0, 0.0, 0.0, 0.0, 0.0, 0.0, 0.0, 0.0, 0.0, 0.0, 0.0, 0.0, 0.0, 0.0, 0.0, 0.0, 0.0, 0.0, 0.0, 0.0, 0.0, 0.0, 0.0, 0.0, 0.0, 0.0, 0.0, 0.0, 0.0, 0.0, 0.0]}, {"dataclass_name": "ActivationRecord", "tokens": [" decay", " very", " quickly", ",", " which", " shows", " the", " low", " rank", " property", " of", " the", " eye", " MR", "F", " data", ",", " and", " forms", " the", " basis", " of", " the", " MC", "\u2010", "based", " reconstruction", ".", " Pl", "ots", " were", " generated", " for", " an", " unders", "am", "pling", " factor", " of", " R", " =", " 12", ".", "3", " in", " the", " outer", " region", " of", " k", "\u2010", "space", ",", " which", " results", " in", " a", " total", " unders", "am", "pling", " factor", " of", " 6"], "activations": [0.0, 0.0, 0.0, 0.0, 0.0, 0.0, 0.0, 0.0, 0.0, 0.0, 0.0, 0.0, 0.0, 0.0, 0.0, 0.0, 0.0, 0.0, 0.0, 0.0, 0.0, 0.0, 0.0, 0.0, 0.0, 0.0, 0.0, 0.0, 0.0, 0.0, 0.0, 0.5493587255477905, 0.0, 0.0, 0.0, 0.0, 0.0, 0.0, 0.0, 0.0, 0.0, 0.0, 0.0, 0.0, 0.0, 0.0, 0.0, 0.0, 0.0, 0.0, 0.0, 0.0, 0.0, 0.0, 0.0, 0.0, 0.0, 0.0, 0.0, 0.0, 0.0, 0.0, 0.0, 0.0]}, {"dataclass_name": "ActivationRecord", "tokens": [" adj", "acency", " matrix", " with", " $\\", "alpha", "(", "A", ")", " =", " M", "$.", " Then", ",", " there", " exists", " $", "A", "'\\", "approx", " A", "$", " such", " that", " $\\", "alpha", "(", "A", "')", "=", "M", "$", " and", " ${\\", "textsf", "{", "sb", "}}^{", "*", "}_\\", "ell", "(", "A", "',", "M", ")$", " holds", ".", "\n", "\n", "Comput", "ing", " Degree", " Mat", "rices", " for", " $", "R", "(", "3", ",", "3", ",", "3"], "activations": [0.5402923822402954, 0.0, 0.0, 0.0, 0.0, 0.0, 0.0, 0.0, 0.0, 0.0, 0.0, 0.0, 0.0, 0.0, 0.0, 0.0, 0.0, 0.0, 0.0, 0.0, 0.0, 0.0, 0.0, 0.0, 0.0, 0.0, 0.0, 0.0, 0.0, 0.0, 0.0, 0.0, 0.0, 0.0, 0.0, 0.0, 0.0, 0.0, 0.0, 0.0, 0.0, 0.0, 0.0, 0.0, 0.0, 0.0, 0.0, 0.0, 0.0, 0.0, 0.024305343627929688, 0.0, 0.0, 0.0, 0.0, 0.0, 0.0, 0.0, 0.0, 0.0, 0.0, 0.0, 0.0, 0.0]}, {"dataclass_name": "ActivationRecord", "tokens": [" the", " two", " divis", "ors", " are", " equal", " outside", " the", " exceptional", " locus", " of", " $\\", "g", "$,", " we", " deduce", " from", " the", " Neg", "ativity", " Lemma", " (", "see", " [@", "KM", "],", " Lemma", " 3", ".", "39", ")", " that", " also", " their", " $\\", "g", "$-", "except", "ional", " components", " must", " coincide", ".", " This", " gives", " $", "g", "_*", "[", "V", "']", " =", " \\", "g", "^*", "f", "_*", " [", "V", "]$.", "\n", "\n", "In", " particular"], "activations": [0.0, 0.0, 0.5370081663131714, 0.0, 0.0, 0.0, 0.0, 0.0, 0.0, 0.0, 0.0, 0.0, 0.0, 0.0, 0.0, 0.0, 0.0, 0.0, 0.0, 0.0, 0.0, 0.0, 0.0, 0.0, 0.0, 0.0, 0.0, 0.0, 0.0, 0.0, 0.0, 0.0, 0.0, 0.0, 0.0, 0.0, 0.0, 0.0, 0.0, 0.0, 0.0, 0.0, 0.0, 0.0, 0.0, 0.0, 0.0, 0.0, 0.0, 0.0, 0.0, 0.0, 0.0, 0.0, 0.0, 0.0, 0.0, 0.0, 0.0, 0.0, 0.0, 0.0, 0.0, 0.0]}, {"dataclass_name": "ActivationRecord", "tokens": ["Free", "CAD", " Python", "\n", "  ", "------------------------------------------------", "--------", " ------------------------------------------------", "----------", " ------------------------------------------------", "--", "\n", "  ", "KERN", "                        ", "                        ", "     ", "Comput", "ational", " Geometry", " Al", "gorithms", " Library", " (", "CG", "AL", ")", "           ", "Open", " C", "ascade", " Technology", " (", "OC", "CT", ")", "\n", "  ", "Based", " on", " Construct", "ive", " Solid", " geometry", " (", "CS", "G", ")", "               ", "Based", " on", " boundary", " representation", " (", "B", "-", "rep", ")", "                   ", "\n", "  ", "Pol", "yg", "onal"], "activations": [0.0, 0.0, 0.0, 0.0, 0.0, 0.0, 0.0, 0.0, 0.0, 0.0, 0.0, 0.0, 0.0, 0.0, 0.0, 0.0, 0.0, 0.08436822891235352, 0.34194743633270264, 0.08598017692565918, 0.0, 0.0, 0.0, 0.0, 0.0, 0.0, 0.0, 0.0, 0.0, 0.0, 0.0, 0.0, 0.0, 0.0, 0.0, 0.0, 0.0, 0.0, 0.0, 0.0, 0.0, 0.0, 0.0, 0.0, 0.0, 0.0, 0.0, 0.0, 0.0, 0.0, 0.0, 0.0, 0.0, 0.0, 0.0, 0.0, 0.5331368446350098, 0.0, 0.0, 0.0, 0.0, 0.0, 0.0, 0.0]}, {"dataclass_name": "ActivationRecord", "tokens": ["Pop", " 2", "165", "\n", "\n", "Ch", "arming", " Wells", " exc", "els", " at", " both", " land", " and", " sea", ".", " R", "ows", " of", " attractive", " Georg", "ian", " houses", " and", " fl", "int", " cott", "ages", " snake", " down", " to", " a", " boat", "-", "lined", " qu", "ay", ";", " to", " the", " north", " sits", " a", " vast", " golden", " beach", ",", " backed", " by", " pine", "-", "covered", " d", "unes", ".", "\n", "\n", "1", "S", "ights", "\n", "\n", "Well", "s"], "activations": [0.0, 0.0, 0.0, 0.0, 0.0, 0.0, 0.0, 0.0, 0.5318938493728638, 0.0, 0.0, 0.0, 0.0, 0.0, 0.0, 0.0, 0.0, 0.0, 0.0, 0.0, 0.0, 0.0, 0.0, 0.0, 0.0, 0.0, 0.0, 0.0, 0.0, 0.0, 0.0, 0.0, 0.0, 0.0, 0.0, 0.0, 0.0, 0.0, 0.0, 0.0, 0.0, 0.0, 0.0, 0.0, 0.008994877338409424, 0.0, 0.0, 0.0, 0.0, 0.0, 0.0, 0.0, 0.0, 0.0, 0.0, 0.0, 0.0, 0.0, 0.0, 0.0, 0.0, 0.0, 0.0, 0.0]}, {"dataclass_name": "ActivationRecord", "tokens": [" Instead", ",", " documentary", " cuts", " straight", " to", " farewell", " at", " end", " of", " year", " and", " collective", " crying", " session", ".", "\n", "\n", "It", " was", " at", " this", " point", ",", " about", " fifteen", " minutes", " in", ",", " that", " I", " decided", " to", " change", " channels", " for", " fear", " of", " being", " plunged", " into", " state", " of", " irreversible", " depression", ".", "\n", "\n", "Speaking", " of", " dogs", ",", " I", " had", " planned", " to", " share", " some", " footage", " of", " another", " Sh", "ins", "uk"], "activations": [0.0, 0.0, 0.0, 0.0, 0.0, 0.0, 0.0, 0.0, 0.0, 0.0, 0.0, 0.0, 0.531378984451294, 0.0, 0.0, 0.0, 0.0, 0.0, 0.0, 0.0, 0.0, 0.0, 0.0, 0.0, 0.0, 0.2160879373550415, 0.0, 0.0, 0.0, 0.0, 0.0, 0.0, 0.0, 0.0, 0.0, 0.0, 0.0, 0.0, 0.0, 0.0, 0.0, 0.0, 0.0, 0.0, 0.0, 0.0, 0.0, 0.0, 0.0, 0.0, 0.0, 0.0, 0.0, 0.0, 0.0, 0.0, 0.0, 0.0, 0.0, 0.0, 0.0, 0.0, 0.0, 0.0]}]}