{"dataclass_name": "NeuronRecord", "neuron_id": {"dataclass_name": "NeuronId", "layer_index": 3, "neuron_index": 2878}, "most_positive_activation_records": [{"dataclass_name": "ActivationRecord", "tokens": [" Instead", ",", " documentary", " cuts", " straight", " to", " farewell", " at", " end", " of", " year", " and", " collective", " crying", " session", ".", "\n", "\n", "It", " was", " at", " this", " point", ",", " about", " fifteen", " minutes", " in", ",", " that", " I", " decided", " to", " change", " channels", " for", " fear", " of", " being", " plunged", " into", " state", " of", " irreversible", " depression", ".", "\n", "\n", "Speaking", " of", " dogs", ",", " I", " had", " planned", " to", " share", " some", " footage", " of", " another", " Sh", "ins", "uk"], "activations": [0.0, 0.0, 0.0, 0.0, 0.0, 0.0, 0.0, 0.0, 0.0, 0.0, 0.0, 0.0, 0.0, 0.0, 0.0, 0.0, 0.0, 0.0, 0.0, 0.0, 0.0, 0.0, 0.0, 0.0, 0.0, 0.0, 0.0, 0.0, 0.0, 0.0, 0.0, 0.0, 0.0, 0.0, 0.0, 0.0, 0.0, 0.0, 0.0, 0.0, 0.0, 0.0, 0.0, 0.0, 0.0, 0.0, 0.0, 0.0, 0.0, 0.0, 0.0, 0.0, 0.0, 0.0, 0.08677315711975098, 0.0, 0.4111584424972534, 2.1145269870758057, 0.7767460346221924, 0.0, 0.0, 0.0, 0.0, 0.0]}, {"dataclass_name": "ActivationRecord", "tokens": [" or", " call", " an", " attorney", " which", " was", " denied", " by", " Assistant", " Jail", " Administrator", ",", " Richard", " Cl", "u", "key", ",", " who", " stated", " that", " it", " did", " not", " meet", " the", " criteria", " of", " a", " defined", " grievance", " and", " it", " did", " not", " present", " a", " griev", "able", " issue", ".", " On", " an", " unspecified", " date", " Simpson", " submitted", " a", " request", " form", " asking", " the", " jail", " administration", " to", " provide", " the", " address", " for", " his", " associate", ",", " providing", " them", " with"], "activations": [0.0, 0.0, 0.0, 0.0, 0.0, 0.0, 0.20406615734100342, 0.0, 0.0, 0.0, 0.0, 0.0, 0.0, 0.0, 0.0, 0.0, 0.0, 0.0, 0.0, 0.0, 0.0, 0.0, 0.0, 0.0, 0.0, 0.0, 0.0, 0.0, 0.0, 0.0, 0.0, 0.0, 0.0, 0.0, 0.0, 0.9077259302139282, 0.3331141471862793, 0.6897011995315552, 0.0, 0.0, 0.0, 0.0, 0.0, 0.0, 0.0, 1.434387445449829, 1.9458742141723633, 0.7165850400924683, 0.6796413660049438, 0.0, 0.0, 0.0, 0.0, 0.0, 0.045855164527893066, 0.48549556732177734, 0.0, 0.0, 0.011217474937438965, 0.0, 0.0, 0.0, 0.12100183963775635, 1.458662748336792]}, {"dataclass_name": "ActivationRecord", "tokens": [" disp", "el", " the", " myths", ",\"", " said", " Wood", ".", "\n", "\n", "So", " what", " should", " Google", " do", "?", " Hughes", " said", " it", " should", " be", " clearer", " about", " what", " the", " ruling", " entitled", " the", " citizen", " to", " ask", " for", ".", "\n", "\n", "\"", "Google", " should", " make", " it", " clear", " how", " many", " people", " they", " are", " turning", " down", ",", " as", " well", " as", " how", " many", " succeed", ".", " If", " people", " get", " the", " impression", " they", " are", " all"], "activations": [0.0, 0.0, 0.0, 0.0, 0.0, 0.0, 0.0, 0.0, 0.0, 0.0, 0.0, 0.0, 0.0, 0.0, 0.0, 0.0, 0.0, 0.0, 0.0, 0.0, 0.0, 0.0, 0.0, 0.0, 0.0, 0.0, 0.0, 0.0, 0.0, 0.3669525384902954, 0.0, 0.9089194536209106, 0.0, 0.0, 0.0, 0.0, 0.0, 0.0, 0.0, 0.0, 0.0, 0.0, 0.0, 0.0, 0.0, 0.0, 0.0, 0.38613247871398926, 0.0, 0.0, 0.0, 0.0, 0.0, 0.0, 0.0, 0.0, 0.0, 0.0, 0.2606281042098999, 1.664700984954834, 0.0, 0.0, 0.0, 0.0]}, {"dataclass_name": "ActivationRecord", "tokens": [" sentenced", " to", " concurrent", " sentences", ",", " the", " Written", " Jud", "gement", " and", " Sent", "ence", ",", " and", " Mit", "imus", " failed", " to", " stip", "ulate", " that", " sentence", " was", " concurrent", "[", "?", "]", "\n", "2", ".", " Did", " the", " District", " Court", " [", "err", "]", " by", " denying", " Appellant", "'s", " Motion", " to", " Correct", " ...", " an", " IL", "LE", "GAL", " Sent", "ence", ",", " which", " was", " filed", " because", " the", " Court", " did", " not", " award", " credit", " for", " time"], "activations": [0.0, 0.0, 0.03000020980834961, 0.0, 0.0, 0.0, 0.0, 0.0, 0.0, 0.0, 0.0, 0.0, 0.0, 0.0, 0.0, 0.0, 0.0, 0.0, 0.0, 0.0, 0.0, 0.0, 0.0, 0.0, 0.0, 0.0, 0.0, 0.0, 0.0, 0.0, 0.0, 0.0, 0.0, 0.0, 0.0, 0.0, 0.0, 0.0, 0.0, 0.0, 1.6560919284820557, 0.6034388542175293, 0.002222418785095215, 0.0, 0.0, 0.22586441040039062, 0.0, 0.0, 0.0, 0.6412969827651978, 0.0, 0.0, 0.0, 0.0, 0.07123875617980957, 0.0, 0.0, 0.0, 0.0, 0.0, 0.1680537462234497, 0.9122103452682495, 0.7760381698608398, 0.16812872886657715]}, {"dataclass_name": "ActivationRecord", "tokens": [" of", " his", "\n", "un", "requ", "ited", " love", " that", " he", " wasn", "'t", " a", " w", "imp", " anymore", ",\"", " B", "ia", "fore", " said", ".", "\n", "During", " the", " trial", ",", " prosecutors", " detailed", " Far", "ley", "'s", " 3", " 1", "/", "2", "-", "year", " obsess", "ive", " pursuit", " of", "\n", "L", "aura", " Black", ".", " He", " sent", " her", " more", " than", " 100", " letters", ",", " followed", " her", " day", " and", " night", ",", "\n", "left", " gifts", " on"], "activations": [0.0, 0.0, 0.0, 0.0, 0.0, 0.0, 0.0, 0.0, 0.0, 0.0, 0.0, 0.0, 0.0, 0.0, 0.0, 0.0, 0.0, 0.0, 0.0, 0.0, 0.0, 0.0, 0.0, 0.0, 0.0, 0.0, 0.0, 0.30670666694641113, 0.0, 0.0, 0.3288367986679077, 0.6137568950653076, 0.0977480411529541, 0.0, 0.17645740509033203, 0.0, 0.1414661407470703, 0.0, 0.0, 0.0, 0.0, 0.0, 0.0, 0.0, 0.0, 0.0, 0.0, 0.0, 0.708915114402771, 1.265967845916748, 1.0246860980987549, 1.5114688873291016, 1.6074073314666748, 1.0244758129119873, 0.0, 0.0, 0.0, 0.0, 0.0, 0.0, 0.0, 0.0, 0.0, 0.0]}, {"dataclass_name": "ActivationRecord", "tokens": [" Martin", " Luther", " King", " Jr", ".", " pre", "ached", " \u2014", " Holder", " said", " that", " he", " will", " soon", " unve", "il", " long", "-", "planned", " Justice", " Department", " guidance", " aimed", " at", " ending", " racial", " profiling", " by", " federal", " law", " enforcement", ".", "\n", "\n", "\u201c", "This", " will", " institute", " rigorous", " new", " standards", " \u2014", " and", " robust", " safe", "guards", " \u2014", " to", " help", " end", " racial", " profiling", ",", " once", " and", " for", " all", ",\u201d", " Holder", " said", ".", " \u201c", "This", " new"], "activations": [0.0, 0.0, 0.0, 0.0, 0.0, 0.0, 0.0, 0.0, 0.0, 0.0, 0.0, 0.0, 0.0, 0.0, 0.0, 0.860012412071228, 1.6029243469238281, 0.6526637077331543, 0.9764738082885742, 0.0, 0.9846522808074951, 0.7506527900695801, 0.0, 0.0, 0.0, 0.0, 0.0, 0.0, 0.0, 0.0, 0.0, 0.0, 0.0, 0.0, 0.0, 0.0, 0.0, 0.0, 0.21930181980133057, 0.4213542938232422, 0.0, 0.0, 0.06488275527954102, 0.0, 0.0, 0.0, 0.0, 0.0, 0.0, 0.0, 0.0, 0.0, 0.0, 0.0, 0.0, 0.0, 0.0, 0.0, 0.0, 0.0, 0.0, 0.0, 0.0, 0.0]}, {"dataclass_name": "ActivationRecord", "tokens": [" S", "add", "ler", ".", " When", " he", " finally", " passes", " away", ",", " Leon", " y", "ells", " out", " him", " name", " in", " anguish", ".", "\n", "\n", "So", " this", " moment", " most", " certainly", " provides", " the", " player", " with", " motivation", ".", " And", " there", " are", " multiple", " reasons", " for", " this", ".", " In", " his", " final", " moments", ",", " Luis", " literally", " gives", " the", " player", " the", " primary", " plot", " incentive", " for", " the", " remainder", " of", " the", " game", ":", " stop", " S", "add"], "activations": [0.0, 0.0, 0.0, 0.0, 0.0, 0.0, 0.0, 0.0, 0.0, 0.0, 0.0, 0.0, 0.0, 0.21079480648040771, 0.0, 0.0, 0.0, 0.0, 0.0, 0.0, 0.0, 0.0, 0.0, 0.0, 0.0, 0.0, 0.0, 0.22125184535980225, 0.0, 0.9968390464782715, 0.6684224605560303, 0.0, 0.0, 0.0, 0.0, 0.0, 0.0, 0.0, 0.0, 0.0, 0.0, 0.0, 0.5327361822128296, 0.0, 0.0, 0.0, 0.0, 0.1649458408355713, 0.0, 0.39467787742614746, 1.5395753383636475, 0.7834327220916748, 0.49808311462402344, 0.31993579864501953, 0.0, 0.0, 0.0, 0.0, 0.0, 0.0, 0.0, 0.0, 0.0, 0.0]}, {"dataclass_name": "ActivationRecord", "tokens": [" stay", "\n\n", "                        ", "                     ", "5", "\n", "\f", "the", " Initial", " Hearing", " and", " further", " proceedings", " in", " this", " Court", " until", " prompt", " resolution", " of", " the", "\n", "appeal", ".\"", " The", " trial", " court", " granted", " the", " motion", " and", " stayed", " \"", "all", " further", " proceedings", " in", " these", "\n", "claims", " pending", " the", " completion", " of", " the", " [", "S", "IF", "'s", "]", " appeal", "\"", " and", " cancelled", " \"", "the", " Initial", "\n", "(", "Sched", "uling", ")", " Hearing", " scheduled"], "activations": [0.0, 0.0, 0.0, 0.0, 0.0, 0.0, 0.0, 0.0, 0.0, 0.0, 0.0, 0.0, 0.0, 0.0, 0.0, 0.0, 0.0, 0.0, 0.0, 0.0, 0.0, 0.0, 0.0, 0.0, 0.0, 0.0, 0.0, 0.0, 0.3786342144012451, 0.006957888603210449, 0.0, 0.0, 0.0, 0.07859468460083008, 0.6174577474594116, 0.0, 0.0, 0.0, 0.0, 0.0, 0.0, 0.0, 0.09494209289550781, 1.1366617679595947, 1.312652826309204, 0.7821907997131348, 0.0, 0.0, 0.467570424079895, 1.5348618030548096, 0.002264261245727539, 0.12136542797088623, 0.0, 0.6697989702224731, 0.6210423707962036, 0.9487595558166504, 0.6867187023162842, 0.23763692378997803, 0.2978161573410034, 0.0, 0.0, 0.43958938121795654, 0.0, 0.0]}, {"dataclass_name": "ActivationRecord", "tokens": [" at", " the", " scene", " took", " Shel", "ton", " to", " the", " last", " place", " where", " he", "\n", "\f", "No", ".", " 12", "-", "58", "69", ",", " Kar", "issa", " Swe", "at", " v", ".", " Joe", " Shel", "ton", "\n\n", "\n", "had", " seen", " the", " suspect", ".", " Shel", "ton", " deployed", " Memphis", " using", " a", " tracking", " harness", " and", " fifteen", "-", "foot", "\n", "\n", "tracking", " lead", " and", " gave", " Memphis", " the", " command", " to", " search", " for", " the", " suspect", "."], "activations": [0.0, 0.0, 0.0, 0.0, 0.0, 0.0, 0.0, 0.0, 0.0, 0.0, 0.0, 0.0, 0.0, 0.0, 0.0, 0.0, 0.0, 0.0, 0.0, 0.0, 0.0, 0.0, 0.0, 0.0, 0.0, 0.0, 0.0, 0.0, 0.0, 0.0, 0.0, 0.0, 0.0, 0.0, 0.0, 0.0, 0.0, 0.0, 0.0, 0.0, 0.0, 0.2087717056274414, 0.2876497507095337, 0.0, 0.0, 0.0, 0.0, 0.0, 0.0, 0.0, 0.0, 0.0, 0.0, 0.0, 0.0, 0.04843461513519287, 1.445892095565796, 1.00892972946167, 0.0, 0.0, 0.0, 0.0, 0.0, 0.0]}, {"dataclass_name": "ActivationRecord", "tokens": [" them", " quick", "!", " I", " also", " felt", " the", " same", " way", " about", " Exposure", " To", " A", " B", "illion", "aire", ".", " It", " just", " really", " fell", " flat", " and", " wasn", "\u2019", "t", " worth", " my", " time", " at", " all", ".", "\n", "\n", "I", " really", " liked", " it", " too", "!", " I", " will", " defin", "et", "ly", " be", " trying", " some", " others", " by", " Taylor", " Jenkins", " Reid", "!", "\n", "\n", "Hey", " there", "!", " I", "'m", " a", " Twenty", "-"], "activations": [0.0, 0.0, 0.0, 0.0, 0.0, 0.0, 0.0, 0.0, 0.0, 0.0, 0.0, 0.0, 0.0, 0.0, 0.0, 0.0, 0.0, 0.0, 0.0, 0.0, 0.0, 0.0, 0.0, 0.0, 0.0, 0.0, 0.0, 0.20124328136444092, 0.08482229709625244, 0.0, 0.0, 0.0, 0.0, 0.0, 0.0, 0.0, 0.0, 0.0, 0.0, 0.0, 0.0, 0.0, 0.0, 0.0, 0.0, 0.0, 0.0, 1.3201913833618164, 0.8029849529266357, 0.0, 0.0, 0.0, 0.0, 0.0, 0.0, 0.0, 0.0, 0.0, 0.0, 0.0, 0.0, 0.0, 0.0, 0.0]}, {"dataclass_name": "ActivationRecord", "tokens": ["'t", " take", " two", " things", " into", " account", ".", " I", " wasn", "'t", " familiar", " with", " the", " informant", " that", " disclosed", " Per", "ous", "'", " whereabouts", ".", " I", " wasn", "'t", " sure", " whether", " I", " could", " trust", " him", " or", " not", ",", " and", " I", " wasn", "'t", " about", " to", " march", " blind", "ly", " into", " a", " trap", " on", " the", " '", "say", " so", "'", " of", " an", " informant", " I", " knew", " nothing", " about", ".", " First", ",", " I", " sent", " a"], "activations": [0.0, 0.0, 0.0, 0.0, 0.0, 0.0, 0.0, 0.0, 0.0, 0.0, 0.0, 0.0, 0.0, 0.0, 0.0, 0.0, 0.0, 0.0, 0.09982442855834961, 0.0, 0.0, 0.0, 0.0, 0.0, 0.0, 0.0, 0.0, 0.0, 0.0, 0.0, 0.0, 0.0, 0.0, 0.0, 0.0, 0.0, 0.0, 0.0, 0.0, 0.0, 0.0, 0.0, 0.0, 0.0, 0.0, 0.0, 0.0, 0.0, 0.0, 0.0, 0.0, 0.0, 0.0, 0.0, 0.0, 0.0, 0.0, 0.0, 0.0, 0.0, 0.0, 0.0, 0.0, 1.246649980545044]}, {"dataclass_name": "ActivationRecord", "tokens": ["ish", "church", ".", "org", ".", "uk", ";", "  ", "h", "9", "am", "-", "5", ".", "30", "pm", "),", " with", " a", " splendid", " 18", "th", "-", "century", " sp", "ire", " and", " tower", " divided", " from", " its", " medieval", " n", "ave", ".", "\n", "\n", "4", "Sleep", "ing", " &", " Eating", "\n", "\n", "The", " town", " pub", "s", " offer", " reasonably", " priced", " meals", ",", " but", " budget", " travellers", " will", " struggle", " to", " find", " cheap", " accommodation", ".", "\n"], "activations": [0.0, 0.0, 0.0, 0.0, 0.0, 0.0, 0.0, 0.0, 0.0, 0.0, 0.0, 0.0, 0.0, 0.0, 0.0, 0.0, 0.0, 0.0, 0.0, 0.0, 0.0, 0.0, 0.0, 0.0, 0.0, 0.0, 0.0, 0.0, 0.0, 0.0, 0.0, 0.0, 0.0, 0.0, 0.0, 0.0, 0.0, 0.0, 0.0, 0.0, 0.0, 0.0, 0.0, 0.0, 0.0, 0.0, 0.0, 0.0, 0.0, 0.37000060081481934, 1.1721878051757812, 0.7604023218154907, 0.21882247924804688, 0.0, 0.0, 0.0, 0.0, 0.0, 0.0, 0.0, 0.6085518598556519, 0.05156970024108887, 0.0, 0.0]}, {"dataclass_name": "ActivationRecord", "tokens": [" and", " REM", "AND", "ED", ".", "\n\n\n", "\n", "1", "\n", " This", " statute", " provides", " that", " on", " resent", "encing", " after", " probation", " revocation", ",", " the", " district", " court", " must", " impose", " \"", "any", " other", " sentence", " that", " was", " available", " ...", " at", " the", " time", " of", " the", " initial", " sentencing", ".\"", "  ", "18", " U", ".", "S", ".", "C", ".", " Sec", "s", ".", " 35", "65", "(", "a", ")", " and", " 35", "65", "(", "b", ")", "\n\n"], "activations": [0.0, 0.0, 0.0, 0.0, 0.0, 0.0, 0.0, 0.0, 0.0, 0.0, 0.0, 0.0, 0.0, 0.0, 0.0, 0.0, 0.0, 0.0, 0.0, 0.0, 0.0, 0.0, 0.0, 0.0, 0.0, 0.6756812334060669, 1.1437568664550781, 0.7735069990158081, 0.0, 0.0, 0.0, 0.0, 0.0, 0.0, 0.0, 0.0, 0.0, 0.0, 0.5337443351745605, 0.0, 0.0, 0.0, 0.0, 0.0, 0.0, 0.0, 0.0, 0.0, 0.0, 0.0, 0.0, 0.0, 0.0, 0.0, 0.0, 0.0, 0.0, 0.0, 0.0, 0.0, 0.0, 0.0, 0.0, 0.0]}, {"dataclass_name": "ActivationRecord", "tokens": [" sampling", " of", " subjects", " with", " varying", " degrees", " of", " lifetime", " drug", " experiences", ".", " Cognitive", " functioning", " was", " examined", " in", " 284", " young", " participants", ",", " between", " 22", " and", " 34", " years", ".", " In", " general", ",", " their", " lifetime", " drug", " experience", " was", " moderate", ".", " Participants", " completed", " a", " neuropsych", "ological", " test", " battery", ",", " including", " measures", " for", " verbal", " learning", ",", " memory", " and", " various", " attention", "al", " functions", ".", " Linear", " regression", " analysis", " was", " performed", " to", " investigate"], "activations": [0.0, 0.0, 0.0, 0.0, 0.0, 0.0, 0.0, 0.0, 0.0, 0.0, 0.0, 0.0, 0.0, 0.0, 0.0, 0.0, 0.0, 0.0, 0.0, 0.0, 0.0, 0.0, 0.0, 0.0, 0.0, 0.0, 0.0, 0.0, 0.0, 0.0, 0.0, 0.0, 0.0, 0.0, 0.0, 0.0, 0.0, 0.536919355392456, 0.995079755783081, 0.2958338260650635, 1.1275420188903809, 0.5839376449584961, 0.6446045637130737, 0.0, 0.0, 0.0, 0.0, 0.0, 0.0, 0.07444882392883301, 0.0, 0.014432907104492188, 0.05080986022949219, 0.0, 0.0, 0.0, 0.0, 0.0, 0.0, 0.0, 0.0, 0.0, 0.0, 0.0]}, {"dataclass_name": "ActivationRecord", "tokens": ["Defendant", " testified", " that", " Tony", "a", " stayed", " in", " the", "\n", "\n", "b", "ath", "room", " upstairs", " while", " D", ".", "R", ".", " went", " down", " to", " the", " basement", " and", " took", " a", "\n", "\n", "sh", "ower", ".", " ", "\u00a0", "He", " testified", " that", " he", " stayed", " in", " the", " kitchen", " and", " did", " not", " go", "\n", "\n", "into", " the", " basement", " until", " D", ".", "R", ".", " had", " already", " gone", " back", " upstairs", " into", "\n", "\n"], "activations": [0.0, 0.0, 0.0, 0.0, 0.0, 0.0, 0.0, 0.0, 0.0, 0.0, 0.0, 0.0, 0.0, 0.0, 0.0, 0.0, 0.0, 0.0, 0.0, 0.0, 0.0, 0.0, 0.0, 0.0, 0.0, 0.16873037815093994, 1.0749242305755615, 0.8546295166015625, 0.4770081043243408, 0.3716529607772827, 0.8331459760665894, 0.0, 0.0, 0.0, 0.0, 0.0, 0.0, 0.0, 0.0, 0.0, 0.0, 0.0, 0.0, 0.0, 0.0, 0.0, 0.0, 0.0, 0.0, 0.0, 0.0, 0.0, 0.0, 0.0, 0.0, 0.0, 0.0, 0.0, 0.0, 0.0, 0.0, 0.0, 0.0, 0.0]}, {"dataclass_name": "ActivationRecord", "tokens": [" addition", " to", " lead", ".", "\n", "\n", "Exper", "iments", " have", " been", " made", " to", " provide", " calibrated", " kinetic", " energy", " values", " for", " AES", " peaks", " in", " order", " to", " calibr", "ate", " Aug", "er", " electron", " spectrom", "eters", " of", " various", " resolving", " powers", ".", " The", " kinetic", " energies", " are", " measured", " using", " a", " V", "G", " Scientific", " ESC", "AL", "AB", " 2", " which", " has", " power", " supplies", " appropriate", " for", " AES", " measurements", " in", " both", " the", " constant", " \u0394", "E", " and"], "activations": [0.0, 0.0, 0.0, 0.0, 0.0, 0.0, 0.0, 0.0, 0.0, 0.0, 0.0, 0.0, 0.0, 0.5057528018951416, 1.0389726161956787, 0.5420130491256714, 0.5231126546859741, 0.0, 0.0, 0.0, 0.0, 0.0, 0.0, 0.0, 0.0, 0.0, 0.0, 0.0, 0.2527480125427246, 0.0, 0.0, 0.0, 0.0, 0.0, 0.0, 0.0, 0.0, 0.0, 0.0, 0.0, 0.0, 0.0, 0.0, 0.0, 0.0, 0.0, 0.0, 0.0, 0.0, 0.0, 0.0, 0.0, 0.0, 0.0, 0.0, 0.0, 0.0, 0.0, 0.0, 0.0, 0.0, 0.0, 0.0, 0.0]}, {"dataclass_name": "ActivationRecord", "tokens": ["  ", "as", " his", " weapon", ".", "\n", "\n", "Sc", "orp", "io", " is", " portrayed", " by", " .", "\n", "\n", "Z", "and", "abar", "udo", "\n", ",", " the", " main", " antagonist", " of", " U", "chu", " Sent", "ai", " Ky", "ur", "anger", ":", " Episode", " of", " St", "inger", ",", " is", " the", " Kar", "o", " of", " the", "  ", "from", "  ", "in", " the", " Aqu", "ila", " System", ".", " He", " is", " armed", " with", " the", "  ", "sw", "ord", ".", " He"], "activations": [0.0, 0.0, 0.0, 0.0, 0.0, 0.0, 0.0, 0.0, 0.0, 0.0, 0.0, 0.0, 0.0, 0.0, 0.0, 0.0, 0.0, 0.0, 0.0, 0.0, 0.0, 0.0, 0.0, 0.0, 0.0, 0.0, 0.0, 0.0, 0.0, 0.0, 0.0, 0.0, 0.0, 0.0, 0.0, 0.0, 0.0, 0.0, 0.0, 0.0, 0.0, 0.0, 0.0, 0.0, 0.0, 0.0, 0.0, 0.0, 0.0, 0.0, 0.0, 0.0, 0.0, 0.0, 0.0, 0.0, 0.0, 0.39045560359954834, 1.0246052742004395, 0.6407574415206909, 0.0, 0.0, 0.0, 0.0]}, {"dataclass_name": "ActivationRecord", "tokens": [" Klein", " said", " that", " Con", "ant", " did", " not", " respond", " to", " further", " requests", " for", " comment", " on", " this", " issue", ".", "\n", "\n", "As", " for", " Con", "ant", "\u2019", "s", " comment", " in", " April", " about", " Rubio", " insisting", " on", " a", " \u201c", "length", "y", " process", " to", " review", " this", " legislation", " before", " votes", " are", " taken", ",\u201d", " that", " seems", " to", " have", " gone", " with", " the", " wind", " as", " well", ".", "Esc", "orts", " Service", " in", " Lah", "ore", "\n"], "activations": [0.0, 0.0, 0.0, 0.0, 0.0, 0.0, 0.0, 0.029915571212768555, 0.394353985786438, 0.6562238931655884, 0.4555532932281494, 1.0123541355133057, 0.19880568981170654, 0.0, 0.0, 0.0, 0.0, 0.0, 0.0, 0.0, 0.0, 0.0, 0.0, 0.0, 0.0, 0.0, 0.0, 0.0, 0.0, 0.0, 0.0, 0.0, 0.1468890905380249, 0.0, 0.0, 0.11308252811431885, 0.0, 0.0, 0.31312859058380127, 0.36693549156188965, 0.0, 0.0, 0.0, 0.0, 0.0, 0.0, 0.0, 0.0, 0.0, 0.0, 0.0, 0.0, 0.0, 0.0, 0.0, 0.0, 0.0, 0.0, 0.0, 0.0, 0.0, 0.0, 0.0, 0.0]}, {"dataclass_name": "ActivationRecord", "tokens": ["\\[", "sec", ":", "abs", "\\]", " introduces", " an", " *", "ab", "st", "raction", "*,", " called", " degree", " matrices", ",", " Section", "\u00a0", "\\[", "sec", ":", "333", "13", "\\]", " demonstrates", " how", " to", " compute", " degree", " matrices", " for", " ${{\\", "cal", " R", "}}(", "3", ",", "3", ",", "3", ";", "13", ")$,", " and", " Section", "\u00a0", "\\[", "sec", ":", "333", "13", "b", "\\]", " shows", " how", " to", " use", " the", " degree", " matrices", " to", " compute", " ${{\\", "cal"], "activations": [0.06183505058288574, 0.0, 0.0, 0.0, 0.0, 0.0, 0.0, 0.0, 0.0, 0.0, 0.0, 0.0, 0.0, 0.0, 0.0, 0.0, 0.0, 0.0, 0.0, 0.0, 0.0, 0.0, 0.0, 0.0, 0.0, 0.0, 0.0, 0.26724278926849365, 0.3149906396865845, 0.25813448429107666, 0.0, 0.0, 0.0, 0.0, 0.0, 0.0, 0.0, 0.0, 0.0, 0.0, 0.0, 0.0, 0.0, 0.0, 0.0, 0.0, 0.0, 0.0, 0.0, 0.0, 0.0, 0.0, 0.0, 0.0, 0.0, 0.0, 0.0, 0.0, 0.0, 0.0, 0.0, 0.9175307750701904, 0.26487433910369873, 0.0]}, {"dataclass_name": "ActivationRecord", "tokens": [" Wood", "pe", "cker", ".", "\n", "\n", "The", " school", " year", " is", " coming", " to", " an", " end", ",", " and", " you", " will", " find", " a", " Student", " Self", "-", "ref", "lection", " Sheet", ",", " for", " learners", " to", " reflect", " on", " their", " learning", " process", ".", " Gam", "ification", " in", " the", " E", "FL", " Class", "room", " presents", " different", " apps", " with", " which", " students", " can", " revise", " concepts", " in", " a", " fun", " way", ".", "\n", "\n", "There", " is", " the", " life"], "activations": [0.0, 0.0, 0.0, 0.0, 0.0, 0.0, 0.0, 0.0, 0.0, 0.0, 0.0, 0.0, 0.0, 0.0, 0.0, 0.0, 0.0, 0.0, 0.0, 0.0, 0.0, 0.0, 0.0, 0.0, 0.0, 0.0, 0.0, 0.0, 0.0, 0.0, 0.0, 0.0, 0.0, 0.0, 0.0, 0.0, 0.0, 0.0, 0.0, 0.0, 0.0, 0.0, 0.0, 0.0, 0.0, 0.3660001754760742, 0.2580770254135132, 0.0, 0.0, 0.0, 0.0, 0.879101037979126, 0.6091493368148804, 0.0, 0.0, 0.0, 0.0, 0.0, 0.0, 0.0, 0.0, 0.0, 0.0, 0.0]}, {"dataclass_name": "ActivationRecord", "tokens": [" If", " Magazine", ",", " \"", "We", " were", " a", " bit", " curious", " to", " know", " what", " it", " was", " about", " it", " that", " could", " appeal", " to", " a", " 16", "-", "year", "-", "old", " and", " a", " 70", "-", "year", "-", "old", ".", " Ph", "ry", "ne", " is", " one", " of", " the", " first", " femin", "ists", ".", " She", " chooses", " to", " live", " alone", ",", " she", " chooses", " not", " to", " get", " married", ".", " She", "'s", " got", " many", " lovers", "."], "activations": [0.0, 0.0, 0.0, 0.0, 0.0, 0.0, 0.0, 0.0, 0.0, 0.0, 0.0, 0.0, 0.0, 0.0, 0.0, 0.0, 0.0, 0.0, 0.0, 0.0, 0.0, 0.0, 0.0, 0.0, 0.0, 0.0, 0.0, 0.0, 0.0, 0.0, 0.0, 0.0, 0.0, 0.0, 0.0, 0.0, 0.0, 0.0, 0.0, 0.0, 0.0, 0.0, 0.0, 0.0, 0.0, 0.0, 0.0, 0.0, 0.0, 0.0, 0.0, 0.0, 0.0, 0.0, 0.0, 0.0, 0.0, 0.0, 0.0, 0.0, 0.0, 0.873151421546936, 0.0, 0.0]}, {"dataclass_name": "ActivationRecord", "tokens": [" assay", " kit", ").", "\n", "\n", "Card", "iac", " TG", " measurements", " were", " taken", " from", " the", " hearts", " of", " 20", " female", " flies", " dissected", " in", " artificial", " hem", "ol", "ymph", ".", " Care", " was", " taken", " to", " remove", " as", " much", " adipose", " tissue", " and", " other", " heart", "-", "associated", " cells", " from", " the", " heart", " as", " possible", ".", " Pre", "par", "ations", " were", " washed", " two", " times", " with", " PBS", ".", " Using", " fine", " force", "ps", ",", " the", " hearts", " were"], "activations": [0.0, 0.0, 0.0, 0.0, 0.0, 0.0, 0.0, 0.0, 0.0, 0.0, 0.0, 0.0, 0.0, 0.0, 0.0, 0.0, 0.0, 0.0, 0.0, 0.0, 0.0, 0.0, 0.0, 0.0, 0.0, 0.0, 0.0, 0.0, 0.0, 0.0, 0.0, 0.0, 0.32381391525268555, 0.3684045076370239, 0.0, 0.0, 0.0, 0.0, 0.0, 0.0, 0.0, 0.0, 0.0, 0.0, 0.0, 0.0, 0.0, 0.0, 0.0, 0.0, 0.0, 0.0, 0.0, 0.8268412351608276, 0.0, 0.0, 0.0, 0.0, 0.0, 0.0, 0.0, 0.0, 0.0, 0.0]}, {"dataclass_name": "ActivationRecord", "tokens": [" In", " contrast", ",", " the", " appellant", " here", " was", " being", " booked", " on", " charges", " of", " participating", " in", " a", " criminal", " drug", " conspiracy", ",", " to", " which", " his", " name", ",", " date", " of", " birth", ",", " and", " Social", " Security", " number", " bore", " no", " direct", " relevance", ".", "\n\n", "\n", "25", "\n", "We", " also", " recognize", " that", " individuals", " under", " arrest", ",", " particularly", " those", " who", " are", " in", " fact", " guilty", " of", " some", " criminal", " activity", ",", " may", " sometimes", " feel"], "activations": [0.0, 0.0, 0.0, 0.0, 0.0, 0.0, 0.0, 0.0, 0.0, 0.0, 0.0, 0.0, 0.0, 0.0, 0.186568021774292, 0.0, 0.0, 0.0, 0.0, 0.0, 0.0, 0.0, 0.0, 0.0, 0.0, 0.0, 0.0, 0.0, 0.0, 0.0, 0.0, 0.0, 0.0, 0.8091646432876587, 0.5999610424041748, 0.30788373947143555, 0.0, 0.0, 0.0, 0.0, 0.0, 0.0, 0.0, 0.0, 0.0, 0.0, 0.0, 0.0, 0.0, 0.0, 0.0, 0.0, 0.0, 0.0, 0.0, 0.0, 0.0, 0.20398950576782227, 0.0, 0.0, 0.0, 0.0, 0.0, 0.0]}, {"dataclass_name": "ActivationRecord", "tokens": ["ys", "Fragment", ".", "new", "Instance", "();", "\n", "                    ", "return", " pages", "[", "position", "];", "\n", "    ", "...", "\n", "    ", "}", "\n", "\n", "Then", ",", " you", " can", " fetch", " and", " cache", " your", " data", " in", " onCreate", "()", " and", " retrieve", " it", " later", " in", " on", "Res", "ume", "()", " in", " your", " respective", " fragments", ".", "\n\n", "Notice", "\n", "\n", "If", " you", "\u2019", "ve", " got", " a", " mental", " health", " condition", " and", " didn", "\u2019", "t"], "activations": [0.0, 0.0, 0.0, 0.0, 0.0, 0.0, 0.0, 0.0, 0.0, 0.0, 0.0, 0.0, 0.0, 0.0, 0.0, 0.0, 0.0, 0.0, 0.0, 0.0, 0.0, 0.0, 0.0, 0.0, 0.0, 0.4167255163192749, 0.009611845016479492, 0.45646166801452637, 0.8074041604995728, 0.31655752658843994, 0.020939111709594727, 0.0, 0.0, 0.0, 0.29463768005371094, 0.25562942028045654, 0.0, 0.0, 0.0, 0.0, 0.0, 0.0, 0.0, 0.0, 0.0, 0.0, 0.0, 0.0, 0.0, 0.0, 0.0, 0.0, 0.0, 0.0, 0.0, 0.0, 0.0, 0.0, 0.0, 0.0, 0.0, 0.0, 0.0, 0.0]}, {"dataclass_name": "ActivationRecord", "tokens": [" the", " teachers", " and", " followers", " of", " and", " asked", " them", " why", " they", " turned", " Gods", " word", " into", " tradition", " for", " their", " own", " purpose", " that", " there", " was", " great", " trouble", " ahead", ".", " Here", " is", " what", " He", " said", " quoting", " the", " Scripture", " from", " Moses", ",", " \"", "Hon", "or", " you", " father", " and", " mother", " and", " wh", "oso", "ever", " abuses", " father", " or", " mother", " must", " surely", " die", ".\"", " He", " then", " took", " a", " deep", " breath", " and", " said"], "activations": [0.0, 0.0, 0.0, 0.0, 0.0, 0.0, 0.0, 0.0, 0.0, 0.0, 0.0, 0.0, 0.0, 0.0, 0.0, 0.0, 0.0, 0.0, 0.0, 0.0, 0.0, 0.0, 0.0, 0.0, 0.0, 0.0, 0.0, 0.0, 0.0, 0.0, 0.0, 0.0, 0.0, 0.0, 0.0, 0.0, 0.0, 0.0, 0.0, 0.0, 0.0, 0.0, 0.0, 0.0, 0.0, 0.0, 0.0, 0.0, 0.0, 0.0, 0.0, 0.0, 0.0, 0.0, 0.0, 0.0, 0.0, 0.0, 0.0, 0.582486629486084, 0.7874218225479126, 0.22237730026245117, 0.0, 0.0]}, {"dataclass_name": "ActivationRecord", "tokens": [" repeated", ".", " \"", "Like", " the", " McCoy", " girl", ".", " She", " didn", "'t", " look", " any", " too", " friendly", " when", " she", " slapped", " your", " face", ".\"", "\n", "\n", "J", "ake", " felt", " himself", " fl", "ushing", ".", " He", " bl", "ust", "ered", ",", " \"", "She", "'ll", " come", " around", ".", " She", " just", " needs", " some", " time", ",", " that", "'s", " all", ".\"", "\n", "\n", "\"", "And", " maybe", " for", " something", " to", " happen", " to", " Bod", "ie", "."], "activations": [0.0, 0.0, 0.0, 0.0, 0.0, 0.0, 0.0, 0.0, 0.0, 0.0, 0.0, 0.0, 0.0, 0.0, 0.0, 0.0, 0.0, 0.0, 0.0, 0.0, 0.0, 0.0, 0.0, 0.0, 0.0, 0.0, 0.0, 0.0, 0.0, 0.0, 0.0, 0.0, 0.0, 0.0, 0.0, 0.0, 0.0, 0.0, 0.0, 0.0, 0.0, 0.0, 0.0, 0.0, 0.7858883142471313, 0.0, 0.0, 0.0, 0.0, 0.0, 0.0, 0.0, 0.0, 0.0, 0.0, 0.0, 0.0, 0.0, 0.0, 0.0, 0.0, 0.0, 0.0, 0.0]}, {"dataclass_name": "ActivationRecord", "tokens": [" of", " the", " device", ")", " component", " in", " which", " the", " device", " driver", " model", " maps", " the", " low", "-", "level", " data", " structures", " of", " the", " physical", " device", " to", " high", " level", " data", " structures", " of", " the", " logical", " device", ".", " Therefore", " the", " Unix", " filesystem", " has", " no", " explicit", " device", " associated", " with", " the", " way", " the", " information", " is", " laid", " down", " as", " it", " deals", " with", " data", " as", " a", " block", " entity", " and", " has", " no", " knowledge", " of", " how"], "activations": [0.0, 0.0, 0.0, 0.0, 0.0, 0.0, 0.0, 0.0, 0.0, 0.0, 0.0, 0.0, 0.0, 0.0, 0.0, 0.0, 0.0, 0.0, 0.0, 0.0, 0.0, 0.0, 0.0, 0.0, 0.0, 0.0, 0.0, 0.0, 0.0, 0.0, 0.0, 0.0, 0.0, 0.0, 0.0, 0.0, 0.0, 0.0, 0.0, 0.0, 0.0, 0.0, 0.0, 0.0, 0.0, 0.0, 0.7850650548934937, 0.21817123889923096, 0.619235634803772, 0.07803177833557129, 0.0, 0.0, 0.0, 0.0, 0.0, 0.007639408111572266, 0.0, 0.0, 0.0, 0.0, 0.0, 0.0, 0.0, 0.0]}, {"dataclass_name": "ActivationRecord", "tokens": [" St", ".", " In", " addition", ",", " Campbell", " wasted", " little", " time", " in", " recruiting", " new", " advisors", " from", " Credit", " Su", "isse", " and", " other", " major", " financial", " firms", ".", "\n", "\n", "D", "omin", "ick", " &", " Domin", "ick", "'s", " first", " branch", " office", " to", " open", " under", " Campbell", "'s", " management", " was", " in", " the", " fall", " of", " 2004", " when", " an", " operation", " in", " Miami", " was", " opened", " to", " focus", " on", " wealthy", " Central", " and", " South", " American", " residents", "."], "activations": [0.0, 0.0, 0.0, 0.0, 0.0, 0.0, 0.0, 0.7682007551193237, 0.5249961614608765, 0.0, 0.0, 0.0, 0.0, 0.0, 0.0, 0.0, 0.0, 0.0, 0.0, 0.0, 0.0, 0.0, 0.0, 0.0, 0.0, 0.0, 0.0, 0.0, 0.0, 0.0, 0.0, 0.0, 0.0, 0.0, 0.0, 0.0, 0.47002458572387695, 0.0, 0.0, 0.0, 0.0, 0.0, 0.0, 0.0, 0.0, 0.0, 0.0, 0.0, 0.0, 0.0, 0.0, 0.0, 0.0, 0.0, 0.0, 0.0, 0.0, 0.0, 0.0, 0.0, 0.0, 0.0, 0.0, 0.0]}, {"dataclass_name": "ActivationRecord", "tokens": [" field", ",", " allowing", " K", "ip", "nis", " to", " score", " standing", " up", ".", "\n", "\n", "Ed", "win", " Enc", "arn", "acion", " added", " a", " two", "-", "run", " hom", "er", " for", " the", " American", " League", " Central", "-", "leading", " Indians", ",", " who", " snapped", " a", " four", "-", "game", " losing", " streak", " and", " avoided", " a", " three", "-", "game", " sweep", " against", " the", " last", "-", "place", " team", " in", " the", " division", ".", "\n", "\n", "Jonathan", " Sch", "oop"], "activations": [0.0, 0.0, 0.0, 0.0, 0.0, 0.0, 0.0, 0.0, 0.0, 0.0, 0.0, 0.0, 0.0, 0.0, 0.0, 0.0, 0.0, 0.0, 0.0, 0.5152018070220947, 0.0, 0.0, 0.0, 0.0, 0.01151883602142334, 0.0, 0.0, 0.0, 0.0, 0.0, 0.0, 0.0, 0.0, 0.0, 0.0, 0.3329981565475464, 0.7459486722946167, 0.0, 0.1342310905456543, 0.5284174680709839, 0.2702900171279907, 0.0, 0.0, 0.0, 0.0, 0.0, 0.0, 0.0, 0.0, 0.0, 0.0, 0.0, 0.0, 0.0, 0.0, 0.0, 0.0, 0.0, 0.0, 0.0, 0.0, 0.0, 0.0, 0.0]}, {"dataclass_name": "ActivationRecord", "tokens": [" warned", " them", " thereby", ".", " Science", " allows", " for", " such", " examples", " to", " serve", " as", " warnings", ".", " In", " any", " case", ",", " Mr", ".", " Truman", " was", " successful", " in", " that", " he", " managed", " to", " warn", " the", " Japanese", " alright", ".[", "3", "]", " As", " a", " matter", " of", " fact", ",", " the", " Americans", " promised", " the", " Japanese", " more", " ruin", " to", " come", " from", " the", " air", ",", " if", " the", " latter", " failed", " to", " concede", " subsequent", " to", " the", " Hiro"], "activations": [0.0, 0.0, 0.0, 0.0, 0.0, 0.0, 0.0, 0.0, 0.0, 0.0, 0.0, 0.0, 0.0, 0.0, 0.0, 0.0, 0.0, 0.0, 0.0, 0.0, 0.0, 0.0, 0.0, 0.0, 0.0, 0.0, 0.0, 0.0, 0.0, 0.0, 0.0, 0.0, 0.0, 0.0, 0.0, 0.0, 0.0, 0.0, 0.0, 0.0, 0.0, 0.0, 0.0, 0.0, 0.0, 0.0, 0.7192082405090332, 0.03738117218017578, 0.0, 0.0, 0.0, 0.0, 0.0, 0.0, 0.0, 0.0, 0.0, 0.0, 0.0, 0.07380068302154541, 0.5414148569107056, 0.004718422889709473, 0.0, 0.0]}, {"dataclass_name": "ActivationRecord", "tokens": [" et", " all", "umer", " le", " fe", "u", " dess", "ous", ".", " \u00ab", " A", "vant", " tout", ",", " dit", " la", " vie", "ille", ",", " nous", " all", "ons", " faire", " cu", "ire", " le", " pain", " :", " j", "'", "ai", " d\u00e9j\u00e0", " fait", " ch", "au", "ffer", " le", " four", " et", " la", " p", "\u00e2te", " est", " p", "\u00e9t", "rie", ".", " \u00bb", " Et", " elle", " p", "ous", "sa", " la", " mal", "he", "ure", "use", " Marg", "ot", " dev", "ant", " l", "'"], "activations": [0.0, 0.0, 0.0, 0.0, 0.0, 0.0, 0.0, 0.0, 0.0, 0.0, 0.0, 0.0, 0.0, 0.0, 0.0, 0.0, 0.0, 0.0, 0.0, 0.0, 0.0, 0.0, 0.3211216926574707, 0.25916099548339844, 0.10179722309112549, 0.0, 0.0, 0.0, 0.0, 0.0, 0.0, 0.686741828918457, 0.08276617527008057, 0.0, 0.0, 0.0, 0.0, 0.0, 0.0, 0.0, 0.0, 0.0, 0.0, 0.0, 0.0, 0.0, 0.0, 0.0, 0.0, 0.0, 0.0, 0.0, 0.0, 0.0, 0.0, 0.0, 0.0, 0.0, 0.0, 0.0, 0.0, 0.0, 0.0, 0.0]}, {"dataclass_name": "ActivationRecord", "tokens": [" challenge", " the", " Government", "'s", " allocation", " because", " they", " did", " not", " challenge", " the", " fairness", " of", " the", " Settlement", " Agreement", " and", ",", " therefore", ",", " the", " Government", "'s", " allocation", " of", " the", " proceeds", " between", " and", " among", " the", " various", " claims", " is", " now", " binding", " against", " the", " Rel", "ators", ".", "\n", "The", " Rel", "ators", ",", " on", " the", " other", " hand", ",", " contend", " that", " they", " were", " never", " put", " on", " notice", " that", " by", " agreeing", " to", " the"], "activations": [0.0, 0.0, 0.0, 0.0, 0.0, 0.0, 0.0, 0.0, 0.0, 0.0, 0.0, 0.0, 0.0, 0.0, 0.19536936283111572, 0.17208194732666016, 0.0, 0.0, 0.0, 0.0, 0.0, 0.0, 0.26038408279418945, 0.0, 0.4304769039154053, 0.4130607843399048, 0.0, 0.0, 0.0, 0.0, 0.0, 0.0, 0.0, 0.0, 0.0, 0.0, 0.0, 0.0, 0.0, 0.0, 0.0, 0.0, 0.0, 0.0, 0.0, 0.0, 0.0, 0.0, 0.0, 0.0, 0.0, 0.0, 0.0, 0.0, 0.0, 0.0, 0.0, 0.05794072151184082, 0.03869926929473877, 0.0, 0.0, 0.0, 0.5591185092926025, 0.6811118125915527]}, {"dataclass_name": "ActivationRecord", "tokens": [" file", "URL", "With", "Path", ":", "[[", "self", " class", "]", " store", "Path", "]];", "\n", "N", "SD", "ictionary", " *", "store", "Meta", " =", " [", "N", "SP", "ers", "istent", "Store", "Coord", "inator", " metadata", "For", "Pers", "istent", "Store", "Of", "Type", ":", "nil", " URL", ":", "store", "URL", " error", ":&", "error", "];", "\n", "\n", "And", " looking", " in", " store", "Meta", " I", " get", " a", " key", " with", "\n", "<", "CF", "String", " 0", "x", "732"], "activations": [0.0, 0.0, 0.0, 0.0, 0.0, 0.0, 0.0, 0.0, 0.0, 0.0, 0.0, 0.0, 0.0, 0.0, 0.0, 0.0, 0.0, 0.0, 0.0, 0.0, 0.0, 0.0, 0.0, 0.0, 0.0, 0.0, 0.0, 0.0, 0.0, 0.0, 0.0, 0.0, 0.0, 0.0, 0.0, 0.0, 0.0, 0.0, 0.0, 0.0, 0.0, 0.0, 0.0, 0.0, 0.0, 0.0, 0.0, 0.0, 0.0, 0.0, 0.0, 0.0, 0.0, 0.0, 0.6758095026016235, 0.11948788166046143, 0.0, 0.0, 0.0, 0.0, 0.0, 0.0, 0.0, 0.0]}, {"dataclass_name": "ActivationRecord", "tokens": [",", " thousands", " of", " people", " began", " ch", "anting", " in", " un", "ison", " \u201c", "N", "ous", " som", "mes", " tous", " des", " cas", "se", "urs", "\u201d", " (\u201c", "We", " are", " all", " riot", "ers", "\u201d)", " until", " we", " reached", " Place", " de", " la", " Nation", ".", "\n", "\n", "This", " last", " event", " might", " seem", " trivial", ";", " in", " reality", ",", " it", " represents", " an", " extremely", " important", " ideological", " shift", " in", " the", " movement", ".", " Since", " the", " beginning", " of", " the"], "activations": [0.0, 0.0, 0.0, 0.0, 0.0, 0.0, 0.6743285655975342, 0.0, 0.0, 0.0, 0.0, 0.0, 0.0, 0.0, 0.0, 0.0, 0.0, 0.0, 0.0, 0.0, 0.0, 0.0, 0.0, 0.0, 0.0, 0.0, 0.0, 0.0, 0.0, 0.0, 0.0, 0.0, 0.0, 0.0, 0.0, 0.0, 0.0, 0.0, 0.0, 0.25544023513793945, 0.0, 0.0, 0.0, 0.0, 0.0, 0.0, 0.0, 0.0, 0.0, 0.0, 0.0, 0.0, 0.0, 0.0, 0.0, 0.0, 0.0, 0.0, 0.0, 0.0, 0.0, 0.0, 0.0, 0.0]}, {"dataclass_name": "ActivationRecord", "tokens": [" is", " now", " being", " merged", " with", " the", " country", "\u2019", "s", " other", " sovereign", " fund", " M", "ub", "ad", "ala", ".", "\n", "\n", "Sar", "aw", "ak", " Report", " has", " further", " exposed", " how", " K", "AQ", " used", " A", "abar", " to", " finance", " his", " own", " company", "\u2019", "s", " bid", " to", " buy", " out", " Europe", "\u2019", "s", " most", " expensive", " building", ",", " the", " Sant", "ander", " complex", " in", " Madrid", ",", " and", " also", " to", " back", " a", " number", " of"], "activations": [0.0, 0.0, 0.0, 0.0, 0.0, 0.0, 0.0, 0.0, 0.0, 0.0, 0.0, 0.0, 0.0, 0.0, 0.0, 0.0, 0.0, 0.0, 0.0, 0.0, 0.0, 0.0, 0.0, 0.0, 0.03316915035247803, 0.0, 0.0, 0.0, 0.0, 0.0, 0.0, 0.0, 0.0, 0.18404781818389893, 0.43017518520355225, 0.3018147945404053, 0.1033163070678711, 0.0, 0.655828595161438, 0.13849937915802002, 0.0, 0.56606125831604, 0.0, 0.0, 0.0, 0.0, 0.0, 0.0, 0.0, 0.0, 0.0, 0.0, 0.0, 0.0, 0.0, 0.0, 0.0, 0.0, 0.0, 0.0, 0.0, 0.0, 0.0, 0.0]}, {"dataclass_name": "ActivationRecord", "tokens": ["/", "day", " and", " 250", " tons", "/", "day", ",", " as", " equivalent", ",", " and", " that", " the", " provision", " of", " section", " 129", " at", " issue", " refers", " to", " 250", " tons", "/", "day", ",", " this", " opinion", " refers", " to", " 250", " tons", "/", "day", " instead", " of", " 225", " Mg", "/", "day", "\n\n", "\n", "8", "\n", " CI", " involves", " injecting", " powdered", " activated", " carbon", " into", " the", " fl", "ue", " gas", " after", " combustion", " but", " before", " the", " gas", " stream", " reaches"], "activations": [0.0, 0.0, 0.0, 0.0, 0.009780645370483398, 0.0, 0.0, 0.0, 0.0, 0.0, 0.0, 0.0, 0.0, 0.0, 0.0, 0.3202040195465088, 0.2165166139602661, 0.0, 0.0, 0.0, 0.0, 0.0, 0.0, 0.0, 0.07517647743225098, 0.0, 0.0, 0.0, 0.0, 0.0, 0.0, 0.0, 0.0, 0.0, 0.0, 0.0, 0.0, 0.0, 0.0, 0.0, 0.0, 0.0, 0.0, 0.0, 0.0, 0.0, 0.0, 0.0, 0.6421149969100952, 0.0, 0.0, 0.0, 0.0, 0.0, 0.0, 0.0, 0.0, 0.0, 0.0, 0.0, 0.0, 0.0, 0.0, 0.0]}, {"dataclass_name": "ActivationRecord", "tokens": ["In", " a", " recent", " interview", " with", " Indian", "public", "ation", "DNA", ",", " Ran", "ve", "er", " opened", " about", " his", " super", "-", "success", "ful", " B", "ollywood", " career", " and", " the", " \u2018", "jour", "ney", " of", " becoming", " a", " hero", ",", " not", " an", " actor", "\u2019", " ...", " In", " a", " recent", " interview", " with", " Indian", "public", "ation", " DNA", ",", " Ran", "ve", "er", " opened", " about", " his", " super", "-", "success", "ful", " B", "ollywood", " career", " and", " the", " \u2018"], "activations": [0.0, 0.0, 0.0, 0.0, 0.0, 0.0, 0.0, 0.0, 0.0, 0.0, 0.0, 0.0, 0.0, 0.0, 0.0, 0.0, 0.0, 0.0, 0.0, 0.0, 0.0, 0.0, 0.0, 0.0, 0.0, 0.0, 0.0, 0.0, 0.0, 0.0, 0.0, 0.0, 0.0, 0.0, 0.0, 0.0, 0.0, 0.0, 0.0, 0.0, 0.6407520771026611, 0.0, 0.0, 0.0, 0.0, 0.0, 0.0, 0.0, 0.0, 0.0, 0.0, 0.032921433448791504, 0.0, 0.0, 0.0, 0.0, 0.0, 0.0, 0.0, 0.0, 0.0, 0.0, 0.0, 0.0]}, {"dataclass_name": "ActivationRecord", "tokens": ["orn", "och", "castle", "hot", "el", ".", "com", ";", " Castle", " St", ";", " s", "/", "d", " \u00a3", "73", "/", "125", ",", " superior", "/", "del", "uxe", " d", " \u00a3", "169", "/", "250", ";", "  ", "p", " W", ")", "\n", "\n", "This", " 16", "th", "-", "century", " former", " bishop", "'s", " palace", " makes", " a", " wonderful", " place", " to", " stay", ",", " particularly", " if", " you", " upgrade", " to", " one", " of", " the", " superior", " rooms", ",", " which", " have"], "activations": [0.0, 0.0, 0.0, 0.0, 0.0, 0.0, 0.0, 0.0, 0.0, 0.0, 0.0, 0.0, 0.0, 0.0, 0.0, 0.0, 0.0, 0.0, 0.0, 0.0, 0.0, 0.0, 0.0, 0.0, 0.0, 0.0, 0.0, 0.0, 0.0, 0.0, 0.0, 0.0, 0.0, 0.0, 0.0, 0.0, 0.0, 0.0, 0.0, 0.0, 0.0, 0.0, 0.0, 0.0, 0.0, 0.5958355665206909, 0.3263862133026123, 0.0, 0.0, 0.0, 0.0, 0.0, 0.0, 0.0, 0.0, 0.0, 0.0, 0.0, 0.0, 0.0, 0.0, 0.0, 0.0, 0.0]}, {"dataclass_name": "ActivationRecord", "tokens": [" he", " was", " elect", "ing", " to", " exercise", " the", " option", ".", " He", " scheduled", " settlement", " for", " October", " 5", ",", " 1978", ".", " As", " the", " chancellor", " found", ":", "\n", "\"", "It", " is", " undisputed", " in", " this", " case", " that", " Mr", ".", " Carl", "ton", " Be", "all", " did", " eventually", " hire", " attorneys", " to", " search", " the", " title", ",", " set", " a", " settlement", " date", ",", " attend", " the", " settlement", ",", " and", " was", " ready", ",", " willing", " and", " able", " to"], "activations": [0.0, 0.0, 0.0, 0.0, 0.0, 0.0, 0.0, 0.0, 0.0, 0.0, 0.0, 0.1595250368118286, 0.0, 0.0, 0.0, 0.0, 0.0, 0.0, 0.0, 0.0, 0.0, 0.0, 0.0, 0.0, 0.0, 0.0, 0.0, 0.0, 0.0, 0.0, 0.0, 0.0, 0.0, 0.0, 0.0, 0.0, 0.0, 0.0, 0.5617499351501465, 0.4791228771209717, 0.0, 0.0, 0.0, 0.0, 0.0, 0.0, 0.0, 0.0, 0.11241531372070312, 0.16251373291015625, 0.0, 0.0, 0.0, 0.0, 0.10032784938812256, 0.0, 0.0, 0.0, 0.0, 0.0, 0.0, 0.0, 0.0, 0.0]}, {"dataclass_name": "ActivationRecord", "tokens": [" C", "b", "\"", " \"", "Sus", "ie", "'s", " mother", " told", " me", " that", " Sus", "ie", "'s", " lost", " in", " the", " corn", ".\"", " \"", "Yeah", ".\"", " \"", "Never", " so", " scared", " in", " my", " life", ",", " I", " put", " the", " pedal", " down", " on", " the", " floor", ",", " and", " grinding", " the", " hell", " out", " of", " the", " gears", ".\"", " \"", "I", " got", " here", " in", " two", " hours", ".\"", " \"", "Pull", "ed", " up", " right", " on", " my", " lawn"], "activations": [0.0, 0.0, 0.0, 0.0, 0.0, 0.0, 0.0, 0.0, 0.0, 0.0, 0.0, 0.0, 0.0, 0.0, 0.0, 0.0, 0.0, 0.0, 0.0, 0.0, 0.0, 0.0, 0.0, 0.0, 0.0, 0.0, 0.0, 0.0, 0.0, 0.0, 0.0, 0.0, 0.549860954284668, 0.0741952657699585, 0.0, 0.0, 0.0, 0.0, 0.0, 0.0, 0.0, 0.0, 0.0, 0.0, 0.0, 0.0, 0.0, 0.0, 0.0, 0.0, 0.0, 0.0, 0.0, 0.0, 0.0, 0.0, 0.0, 0.0, 0.0, 0.0, 0.0, 0.0, 0.0, 0.0]}, {"dataclass_name": "ActivationRecord", "tokens": [".", "co", ".", "uk", ";", " 3", " B", "ells", " Court", ";", "  ", "h", "noon", "-", "mid", "night", ")", "\n", "\n", "Quite", " possibly", " the", " greatest", " idea", " ever", ",", " anytime", ",", " anywhere", ":", " a", " pub", " and", " book", "shop", " rolled", " into", " one", ",", " meaning", " you", " can", " browse", " for", " reading", " material", " before", " settling", " down", " for", " a", " pint", " of", " real", " ale", ".", "\n", "\n", "The", " Front", "PU", "B", "\n", "\n"], "activations": [0.0, 0.0, 0.0, 0.0, 0.0, 0.0, 0.0, 0.0, 0.0, 0.0, 0.0, 0.0, 0.0, 0.0, 0.0, 0.0, 0.0, 0.0, 0.0, 0.0, 0.0, 0.0, 0.0, 0.0, 0.0, 0.0, 0.0, 0.0, 0.0, 0.0, 0.0, 0.0, 0.0, 0.0, 0.0, 0.0, 0.0, 0.0, 0.0, 0.0, 0.0, 0.0, 0.0, 0.12930059432983398, 0.5309947729110718, 0.4988020658493042, 0.0, 0.0, 0.0, 0.14088523387908936, 0.448325514793396, 0.0, 0.06175124645233154, 0.0, 0.0, 0.0, 0.0, 0.0, 0.0, 0.0, 0.0, 0.0, 0.0, 0.0]}, {"dataclass_name": "ActivationRecord", "tokens": [",", " cream", " and", " gold", ";", " a", " restaurant", " by", " Albert", " R", "oux", " completes", " the", " luxury", " package", ".", "\n", "\n", "5", "E", "ating", "\n", "\n", "Vel", "ocity", " Cafe", "CA", "FE", "\n", "\n", "(", "  ", "MAP", "   ", "G", "OOGLE", " MAP", " )", " ;", "  ", "%", "01", "463", "-", "4", "1995", "6", ";", " velocity", "love", ".", "co", ".", "uk", ";", " 1", " Crown", " Ave", ";", " mains", " \u00a3", "4", "-", "7"], "activations": [0.0, 0.0, 0.0, 0.0, 0.0, 0.0, 0.0, 0.0, 0.0, 0.0, 0.0, 0.034192562103271484, 0.5059546232223511, 0.0, 0.0, 0.0, 0.0, 0.0, 0.0, 0.0, 0.0, 0.0, 0.0, 0.0, 0.0, 0.0, 0.0, 0.0, 0.0, 0.0, 0.0, 0.0, 0.0, 0.0, 0.0, 0.0, 0.0, 0.0, 0.0, 0.0, 0.0, 0.0, 0.0, 0.0, 0.0, 0.0, 0.0, 0.0, 0.0, 0.0, 0.0, 0.0, 0.0, 0.0, 0.0, 0.0, 0.0, 0.0, 0.0, 0.0, 0.0, 0.0, 0.0, 0.0]}, {"dataclass_name": "ActivationRecord", "tokens": [" hazard", " rates", " of", " subgroups", ".", " Variables", " reaching", " a", " *", "P", "*\\<", "0", ".", "10", " on", " un", "ivariable", " analyses", " were", " entered", " in", " mult", "ivariable", " models", ",", " and", " further", " backward", " elimination", " was", " applied", " for", " the", " final", " mult", "ivariable", " models", ".", " Conf", "ound", "ers", " included", " in", " final", " models", " were", " the", " following", ":", " quad", "ri", "polar", " lead", ",", " sex", " (", "male", "),", " age", " at", " implantation", ",", " New", " York"], "activations": [0.0, 0.0, 0.0, 0.0, 0.0, 0.0, 0.0, 0.0, 0.0, 0.0, 0.0, 0.0, 0.0, 0.0, 0.0, 0.0, 0.0, 0.0, 0.0, 0.0, 0.0, 0.0, 0.0, 0.0, 0.0, 0.0, 0.0, 0.0, 0.0, 0.0, 0.0, 0.0, 0.0, 0.0, 0.0, 0.5015013217926025, 0.0, 0.0, 0.0, 0.0, 0.0, 0.0, 0.0, 0.0, 0.0, 0.0, 0.0, 0.0, 0.0, 0.0, 0.0, 0.0, 0.0, 0.0, 0.0, 0.0, 0.0, 0.0, 0.0, 0.0, 0.0, 0.0, 0.0, 0.0]}, {"dataclass_name": "ActivationRecord", "tokens": [",", " such", " as", " the", " assessment", " of", " one", "'s", " own", " personality", " traits", " and", " whether", " someone", " would", " cheat", " to", " achieve", " a", " goal", ".", "\n", "\n", "According", " to", " G", ".", " J", "adem", "yr", " and", " Yo", "ji", "y", "f", "us", ",", " the", " perception", " of", " different", " aspect", " in", " the", " interpreting", " theory", " can", " be", " due", " to", " many", " factors", ",", " such", " as", " circumstances", " regarding", " dis", "son", "ance", " and", " controversy", ".", " This"], "activations": [0.0, 0.0, 0.0, 0.0, 0.0, 0.0, 0.0, 0.0, 0.0, 0.0, 0.0, 0.0, 0.0, 0.0, 0.0, 0.0, 0.0, 0.13055896759033203, 0.477394700050354, 0.0, 0.0, 0.0, 0.0, 0.0, 0.0, 0.0, 0.0, 0.0, 0.0, 0.0, 0.0, 0.0, 0.0, 0.0, 0.0, 0.0, 0.0, 0.0, 0.0, 0.0, 0.0, 0.0, 0.0, 0.0, 0.0, 0.0, 0.0, 0.0, 0.0, 0.0, 0.0, 0.0, 0.0, 0.0, 0.0, 0.0, 0.0, 0.0, 0.0, 0.0, 0.0, 0.0, 0.0, 0.0]}, {"dataclass_name": "ActivationRecord", "tokens": [")=", "0", ",", " \n", " \\", "end", "{", "cases", "}$$", "\n", "that", " generates", " the", " sequence", " O", "E", "IS", " A", "0010", "28", ".", " ", "\n", "As", " before", ",", " a", " maxim", "ally", "-", "defined", " analytic", " solution", " $", "g", "$,", " if", " any", ",", " must", " be", " totally", " monotonic", " and", " defined", " for", " all", "  ", "$", "x", "\\", "ge", "0", "$,", " for", " otherwise", " $", " g", "'\\", "circ", " g", "^{-", "1", "}"], "activations": [0.0, 0.0, 0.0, 0.0, 0.0, 0.0, 0.0, 0.0, 0.0, 0.0, 0.0, 0.0027533769607543945, 0.47142112255096436, 0.0, 0.0, 0.0, 0.2424098253250122, 0.0, 0.0, 0.0, 0.0, 0.0, 0.0, 0.0, 0.0, 0.0, 0.0, 0.0, 0.0, 0.0, 0.0, 0.0, 0.0, 0.0, 0.0, 0.0, 0.0, 0.0, 0.0, 0.0, 0.0, 0.0, 0.0, 0.0, 0.0, 0.0, 0.0, 0.0, 0.0, 0.0, 0.0, 0.0, 0.0, 0.0, 0.0, 0.0, 0.0, 0.0, 0.0, 0.0, 0.0, 0.0, 0.0, 0.0]}, {"dataclass_name": "ActivationRecord", "tokens": [" 20", "82", "-", "83", ".", "\n\n", "\n", "3", "\n", " The", " general", " test", " is", " stated", " in", " note", " 1", ",", " supra", "\n\n\n", "Q", ":", "\n", "\n", "jq", "Grid", " Group", "ing", " state", " when", " filtering", "\n", "\n", "I", " am", " using", " a", " filter", " for", " my", " j", "q", "Grid", " grid", ",", " and", " the", " data", " is", " in", " groups", ",", " default", "ing", " first", " state", " of", " collapsed", ".", " If", " a", " user", " open", " a"], "activations": [0.0, 0.0, 0.0, 0.0, 0.0, 0.0, 0.0, 0.0, 0.0, 0.0, 0.0, 0.0, 0.0, 0.0, 0.0, 0.0, 0.0, 0.0, 0.0, 0.0, 0.0, 0.0, 0.0, 0.0, 0.0, 0.0, 0.0, 0.0, 0.0, 0.0, 0.0, 0.0, 0.0, 0.0, 0.0, 0.0, 0.0, 0.0, 0.0, 0.0, 0.0, 0.0, 0.0, 0.0, 0.0, 0.0, 0.0, 0.0, 0.46015310287475586, 0.10344171524047852, 0.0, 0.0, 0.0, 0.0, 0.0, 0.0, 0.0, 0.0, 0.0, 0.0, 0.0, 0.0, 0.0, 0.07435786724090576]}, {"dataclass_name": "ActivationRecord", "tokens": [" v", ".", " Holder", ",", " Nos", ".", " 1902", "-", "ag", " (", "L", "),", " 11", "-", "843", "-", "ag", " (", "Con", "),", " the", " BIA", "\n", "\n", "did", " not", " err", " in", " finding", " that", " the", " petitioner", " failed", " to", " establish", "\n", "\n", "her", " prima", " facie", " eligibility", " for", " relief", " based", " on", " her", " newly", "\n", "\n", "comm", "enced", " practice", " of", " Fal", "un", " G", "ong", " in", " the", " United", " States", " because", "\n", "\n"], "activations": [0.0, 0.0, 0.0, 0.0, 0.0, 0.0, 0.0, 0.26611125469207764, 0.0, 0.0, 0.0, 0.0, 0.0, 0.0, 0.0, 0.0, 0.0, 0.0, 0.0, 0.0, 0.0, 0.0, 0.0, 0.0, 0.0, 0.0, 0.0, 0.0, 0.0, 0.0, 0.0, 0.0, 0.0, 0.45598745346069336, 0.0, 0.0, 0.0, 0.0, 0.0, 0.022220253944396973, 0.0, 0.43483030796051025, 0.0, 0.0, 0.0, 0.09139001369476318, 0.25160861015319824, 0.08262240886688232, 0.016119837760925293, 0.0, 0.0, 0.0, 0.0, 0.0, 0.0, 0.0, 0.0, 0.0, 0.0, 0.0, 0.0, 0.0, 0.0, 0.0]}, {"dataclass_name": "ActivationRecord", "tokens": [" 28", ",", " 1997", ",", " I", " denied", " these", " motions", " on", " the", " ground", " that", " the", " Government", " is", " not", " a", " fiduciary", " of", " the", " settlement", " proceeds", " (", "filed", " document", " #", " 80", ").", " The", " Government", " neither", " expressly", " nor", " implied", "ly", " agreed", " to", " act", " as", " a", " fiduciary", " of", " these", " funds", ".", " Character", "izing", " the", " settlement", " *", "428", " funds", " as", " a", " trust", " fund", " is", " inappropriate", ".", " I", " ruled", ",", " therefore", ","], "activations": [0.0, 0.0, 0.0, 0.0, 0.0, 0.0, 0.4441506862640381, 0.07265865802764893, 0.0, 0.0, 0.0, 0.0, 0.0, 0.0, 0.0, 0.0, 0.0, 0.0, 0.0, 0.0, 0.0, 0.0, 0.0, 0.0, 0.3836413621902466, 0.1853870153427124, 0.0, 0.0, 0.0, 0.0, 0.0, 0.0, 0.0, 0.0, 0.0, 0.0, 0.0, 0.0, 0.0, 0.0, 0.0, 0.0, 0.0, 0.0, 0.0, 0.0, 0.0, 0.0, 0.0, 0.0, 0.0, 0.0, 0.0, 0.0, 0.0, 0.0, 0.0, 0.0, 0.0, 0.0, 0.0, 0.0, 0.0, 0.0]}, {"dataclass_name": "ActivationRecord", "tokens": [" may", " change", " because", " of", " a", " revision", " of", " product", " definitions", " or", " a", " review", " (", "e", ".", "g", ".,", " a", " financial", " and", " performance", " review", ")", " of", " the", " mechanical", " equipment", ".", " Further", ",", " even", " during", " the", " manufacturing", " process", ",", " the", " manufacturer", " of", " the", " mechanical", " equipment", " may", " substitute", " different", " components", " (", "e", ".", "g", ".,", " parts", ")", " from", " different", " suppliers", " to", " customize", " the", " mechanical", " equipment", ",", " to", " meet"], "activations": [0.0, 0.0, 0.0, 0.0, 0.0, 0.0, 0.0, 0.0, 0.0, 0.0, 0.0, 0.0, 0.0, 0.0, 0.0, 0.0, 0.0, 0.0, 0.0, 0.0, 0.0, 0.0, 0.0, 0.0, 0.0, 0.0, 0.0, 0.0, 0.0, 0.0, 0.0, 0.0, 0.0, 0.0, 0.0, 0.0, 0.0, 0.0, 0.0, 0.2541729211807251, 0.24576151371002197, 0.0, 0.0, 0.0, 0.42885828018188477, 0.0, 0.0, 0.0, 0.0, 0.0, 0.0, 0.0, 0.09250128269195557, 0.0, 0.0, 0.0, 0.0, 0.0, 0.0, 0.3050147294998169, 0.0, 0.0, 0.0, 0.0]}, {"dataclass_name": "ActivationRecord", "tokens": [" and", " order", " type", ".", "\n", "I", " was", " using", " the", " ASP", ".", "NET", " menu", " control", " for", " this", " until", " the", " q", "a", " department", " asked", " to", " change", " the", " menu", " to", " expand", " on", " click", " instead", " of", " hover", ".", "  ", "At", " that", " point", ",", " I", " decided", " to", " try", " and", " do", " the", " menu", " with", " a", " simpler", " css", "/", "html", "/", "jquery", " approach", " but", " I", "'ve", " hit", " a", " jam", ".", "\n"], "activations": [0.0, 0.0, 0.0, 0.0, 0.0, 0.0, 0.0, 0.0, 0.0, 0.0, 0.0, 0.0, 0.0, 0.0, 0.0, 0.0, 0.0, 0.0, 0.0, 0.0, 0.0, 0.0, 0.0, 0.0, 0.0, 0.0, 0.0, 0.0, 0.0, 0.0, 0.0, 0.0, 0.0, 0.0, 0.0, 0.0, 0.0, 0.0, 0.0, 0.0, 0.0, 0.0, 0.0, 0.0, 0.0, 0.42794787883758545, 0.0, 0.0, 0.0, 0.0, 0.0, 0.0, 0.0, 0.14102685451507568, 0.0, 0.0, 0.0, 0.0, 0.0, 0.0, 0.0, 0.0, 0.0, 0.0]}]}